{
"meta":{"test_sets":[],"test_metrics":[],"learn_metrics":[{"best_value":"Min","name":"RMSE"}],"launch_mode":"Train","parameters":"","iteration_count":1000,"learn_sets":["learn"],"name":"experiment"},
"iterations":[
{"learn":[14.59871775],"iteration":0,"passed_time":0.1461187531,"remaining_time":145.9726343},
{"learn":[14.22518863],"iteration":1,"passed_time":0.1481948075,"remaining_time":73.94920893},
{"learn":[13.8866124],"iteration":2,"passed_time":0.1497226795,"remaining_time":49.75783715},
{"learn":[13.52356875],"iteration":3,"passed_time":0.1510176543,"remaining_time":37.60339592},
{"learn":[13.18870211],"iteration":4,"passed_time":0.1523492101,"remaining_time":30.3174928},
{"learn":[12.9124226],"iteration":5,"passed_time":0.1535730294,"remaining_time":25.44193187},
{"learn":[12.60003351],"iteration":6,"passed_time":0.1547586721,"remaining_time":21.95362306},
{"learn":[12.32990573],"iteration":7,"passed_time":0.1558223442,"remaining_time":19.32197068},
{"learn":[12.0660619],"iteration":8,"passed_time":0.156925044,"remaining_time":17.27919096},
{"learn":[11.77309809],"iteration":9,"passed_time":0.1578933128,"remaining_time":15.63143797},
{"learn":[11.49227636],"iteration":10,"passed_time":0.158719792,"remaining_time":14.27035221},
{"learn":[11.26264833],"iteration":11,"passed_time":0.1594027296,"remaining_time":13.12415807},
{"learn":[11.04260393],"iteration":12,"passed_time":0.1600304209,"remaining_time":12.15000196},
{"learn":[10.79916926],"iteration":13,"passed_time":0.160620192,"remaining_time":11.31225067},
{"learn":[10.5541002],"iteration":14,"passed_time":0.1612449811,"remaining_time":10.58842042},
{"learn":[10.31918115],"iteration":15,"passed_time":0.1618731517,"remaining_time":9.955198829},
{"learn":[10.10004441],"iteration":16,"passed_time":0.1624610741,"remaining_time":9.394072697},
{"learn":[9.894556723],"iteration":17,"passed_time":0.163071917,"remaining_time":8.896479027},
{"learn":[9.690174082],"iteration":18,"passed_time":0.1636636202,"remaining_time":8.450211127},
{"learn":[9.506034866],"iteration":19,"passed_time":0.1642539466,"remaining_time":8.048443382},
{"learn":[9.338524633],"iteration":20,"passed_time":0.1648377088,"remaining_time":7.684576996},
{"learn":[9.170203312],"iteration":21,"passed_time":0.1656275315,"remaining_time":7.362896629},
{"learn":[9.010299969],"iteration":22,"passed_time":0.1662531277,"remaining_time":7.062143728},
{"learn":[8.843866678],"iteration":23,"passed_time":0.1668423134,"remaining_time":6.784920744},
{"learn":[8.690548059],"iteration":24,"passed_time":0.1673977667,"remaining_time":6.528512903},
{"learn":[8.555307687],"iteration":25,"passed_time":0.1679532189,"remaining_time":6.291785968},
{"learn":[8.413851302],"iteration":26,"passed_time":0.168529398,"remaining_time":6.073300159},
{"learn":[8.29256019],"iteration":27,"passed_time":0.1692185286,"remaining_time":5.874300351},
{"learn":[8.162193833],"iteration":28,"passed_time":0.1711445924,"remaining_time":5.730393078},
{"learn":[8.040736294],"iteration":29,"passed_time":0.1720106795,"remaining_time":5.561678639},
{"learn":[7.921220278],"iteration":30,"passed_time":0.172707323,"remaining_time":5.398496645},
{"learn":[7.809589039],"iteration":31,"passed_time":0.1736519517,"remaining_time":5.25297154},
{"learn":[7.699675801],"iteration":32,"passed_time":0.1745560276,"remaining_time":5.115020566},
{"learn":[7.60645267],"iteration":33,"passed_time":0.1752280389,"remaining_time":4.978537812},
{"learn":[7.498880302],"iteration":34,"passed_time":0.1758372973,"remaining_time":4.848085484},
{"learn":[7.401158744],"iteration":35,"passed_time":0.1764330237,"remaining_time":4.7244843},
{"learn":[7.306431077],"iteration":36,"passed_time":0.1770152245,"remaining_time":4.607180033},
{"learn":[7.223863468],"iteration":37,"passed_time":0.1776151222,"remaining_time":4.496467041},
{"learn":[7.143477682],"iteration":38,"passed_time":0.1781915235,"remaining_time":4.390821899},
{"learn":[7.062817131],"iteration":39,"passed_time":0.1788072296,"remaining_time":4.291373511},
{"learn":[6.990793435],"iteration":40,"passed_time":0.1793895589,"remaining_time":4.195965536},
{"learn":[6.931862224],"iteration":41,"passed_time":0.1799917214,"remaining_time":4.105525454},
{"learn":[6.858296558],"iteration":42,"passed_time":0.1806012263,"remaining_time":4.019427291},
{"learn":[6.786268161],"iteration":43,"passed_time":0.1811938596,"remaining_time":3.936848404},
{"learn":[6.717118549],"iteration":44,"passed_time":0.1817800291,"remaining_time":3.857776173},
{"learn":[6.652948106],"iteration":45,"passed_time":0.1823658861,"remaining_time":3.782109898},
{"learn":[6.589686076],"iteration":46,"passed_time":0.182954502,"remaining_time":3.709694478},
{"learn":[6.531283097],"iteration":47,"passed_time":0.1837898309,"remaining_time":3.64516498},
{"learn":[6.471368031],"iteration":48,"passed_time":0.1845943896,"remaining_time":3.58263805},
{"learn":[6.416481395],"iteration":49,"passed_time":0.1855615078,"remaining_time":3.525668647},
{"learn":[6.369870822],"iteration":50,"passed_time":0.1864209535,"remaining_time":3.46889186},
{"learn":[6.325678067],"iteration":51,"passed_time":0.1871055734,"remaining_time":3.411078531},
{"learn":[6.275766122],"iteration":52,"passed_time":0.1877001071,"remaining_time":3.353811347},
{"learn":[6.224773967],"iteration":53,"passed_time":0.188245864,"remaining_time":3.297788655},
{"learn":[6.182249254],"iteration":54,"passed_time":0.1887854259,"remaining_time":3.243676864},
{"learn":[6.139904173],"iteration":55,"passed_time":0.1893528855,"remaining_time":3.191948641},
{"learn":[6.100525536],"iteration":56,"passed_time":0.1898877988,"remaining_time":3.141477093},
{"learn":[6.062568564],"iteration":57,"passed_time":0.1904302613,"remaining_time":3.092850107},
{"learn":[6.030559288],"iteration":58,"passed_time":0.1910956429,"remaining_time":3.047813559},
{"learn":[5.997931376],"iteration":59,"passed_time":0.1916819003,"remaining_time":3.003016438},
{"learn":[5.964103835],"iteration":60,"passed_time":0.1922544424,"remaining_time":2.959457728},
{"learn":[5.933729724],"iteration":61,"passed_time":0.1928331646,"remaining_time":2.917379168},
{"learn":[5.901932711],"iteration":62,"passed_time":0.1933945633,"remaining_time":2.87636041},
{"learn":[5.873727795],"iteration":63,"passed_time":0.1939674839,"remaining_time":2.836774453},
{"learn":[5.846485734],"iteration":64,"passed_time":0.1945779462,"remaining_time":2.798928918},
{"learn":[5.820630862],"iteration":65,"passed_time":0.1951447931,"remaining_time":2.761594496},
{"learn":[5.793646238],"iteration":66,"passed_time":0.1957230464,"remaining_time":2.725516452},
{"learn":[5.765388646],"iteration":67,"passed_time":0.1963290384,"remaining_time":2.690862703},
{"learn":[5.747073912],"iteration":68,"passed_time":0.196994628,"remaining_time":2.657999981},
{"learn":[5.722315217],"iteration":69,"passed_time":0.1976177314,"remaining_time":2.625492718},
{"learn":[5.699970599],"iteration":70,"passed_time":0.1982028391,"remaining_time":2.593386444},
{"learn":[5.682732647],"iteration":71,"passed_time":0.1993283666,"remaining_time":2.569121169},
{"learn":[5.663525791],"iteration":72,"passed_time":0.2010158641,"remaining_time":2.552626109},
{"learn":[5.642381613],"iteration":73,"passed_time":0.2016342314,"remaining_time":2.523152679},
{"learn":[5.621404779],"iteration":74,"passed_time":0.2021869686,"remaining_time":2.49363928},
{"learn":[5.602460129],"iteration":75,"passed_time":0.202788161,"remaining_time":2.465477115},
{"learn":[5.587337574],"iteration":76,"passed_time":0.2033483145,"remaining_time":2.437538887},
{"learn":[5.572393026],"iteration":77,"passed_time":0.2039034673,"remaining_time":2.41024355},
{"learn":[5.558425806],"iteration":78,"passed_time":0.2044880651,"remaining_time":2.383968456},
{"learn":[5.541518902],"iteration":79,"passed_time":0.2050522695,"remaining_time":2.358101099},
{"learn":[5.526157283],"iteration":80,"passed_time":0.2056222833,"remaining_time":2.332924424},
{"learn":[5.511746977],"iteration":81,"passed_time":0.2061963966,"remaining_time":2.308393806},
{"learn":[5.504975022],"iteration":82,"passed_time":0.2064969889,"remaining_time":2.28141854},
{"learn":[5.493980522],"iteration":83,"passed_time":0.2070511174,"remaining_time":2.257843138},
{"learn":[5.480745463],"iteration":84,"passed_time":0.2076519308,"remaining_time":2.235311961},
{"learn":[5.464052013],"iteration":85,"passed_time":0.2082235992,"remaining_time":2.212981043},
{"learn":[5.449143727],"iteration":86,"passed_time":0.2087532497,"remaining_time":2.19070939},
{"learn":[5.438255432],"iteration":87,"passed_time":0.2093537542,"remaining_time":2.16966618},
{"learn":[5.425927931],"iteration":88,"passed_time":0.2099165722,"remaining_time":2.148696599},
{"learn":[5.412331217],"iteration":89,"passed_time":0.2104687687,"remaining_time":2.128073106},
{"learn":[5.400691499],"iteration":90,"passed_time":0.2110003207,"remaining_time":2.107684522},
{"learn":[5.391618744],"iteration":91,"passed_time":0.2115215591,"remaining_time":2.087625822},
{"learn":[5.380766572],"iteration":92,"passed_time":0.2120523394,"remaining_time":2.068080343},
{"learn":[5.372207183],"iteration":93,"passed_time":0.212601717,"remaining_time":2.049118677},
{"learn":[5.362918837],"iteration":94,"passed_time":0.2132293093,"remaining_time":2.031289736},
{"learn":[5.348292324],"iteration":95,"passed_time":0.2141145274,"remaining_time":2.016245133},
{"learn":[5.339772295],"iteration":96,"passed_time":0.2148776546,"remaining_time":2.000355898},
{"learn":[5.331515983],"iteration":97,"passed_time":0.215667711,"remaining_time":1.985023218},
{"learn":[5.323861644],"iteration":98,"passed_time":0.2164838689,"remaining_time":1.970221877},
{"learn":[5.313277281],"iteration":99,"passed_time":0.2170769555,"remaining_time":1.953692599},
{"learn":[5.30685627],"iteration":100,"passed_time":0.2176100234,"remaining_time":1.936944664},
{"learn":[5.29652059],"iteration":101,"passed_time":0.2182154383,"remaining_time":1.921151604},
{"learn":[5.288350766],"iteration":102,"passed_time":0.2188331888,"remaining_time":1.905760877},
{"learn":[5.27993346],"iteration":103,"passed_time":0.2194156002,"remaining_time":1.890349786},
{"learn":[5.271789139],"iteration":104,"passed_time":0.2200048198,"remaining_time":1.875279178},
{"learn":[5.262684686],"iteration":105,"passed_time":0.2205619587,"remaining_time":1.860211237},
{"learn":[5.251619772],"iteration":106,"passed_time":0.2211415207,"remaining_time":1.845601664},
{"learn":[5.241012171],"iteration":107,"passed_time":0.2217078033,"remaining_time":1.831142227},
{"learn":[5.232684032],"iteration":108,"passed_time":0.2222730344,"remaining_time":1.816929116},
{"learn":[5.224267141],"iteration":109,"passed_time":0.2228506275,"remaining_time":1.803064168},
{"learn":[5.216324968],"iteration":110,"passed_time":0.223427004,"remaining_time":1.789428888},
{"learn":[5.211102527],"iteration":111,"passed_time":0.2239964564,"remaining_time":1.775971904},
{"learn":[5.206364257],"iteration":112,"passed_time":0.2245589437,"remaining_time":1.762688346},
{"learn":[5.196937641],"iteration":113,"passed_time":0.2251095916,"remaining_time":1.749535949},
{"learn":[5.190746047],"iteration":114,"passed_time":0.2256812597,"remaining_time":1.736764477},
{"learn":[5.181885213],"iteration":115,"passed_time":0.2262389771,"remaining_time":1.724097032},
{"learn":[5.178293568],"iteration":116,"passed_time":0.2266770455,"remaining_time":1.7107336},
{"learn":[5.170991438],"iteration":117,"passed_time":0.227281645,"remaining_time":1.698833991},
{"learn":[5.166257212],"iteration":118,"passed_time":0.2278405241,"remaining_time":1.686785729},
{"learn":[5.161421246],"iteration":119,"passed_time":0.2287634032,"remaining_time":1.67759829},
{"learn":[5.158223542],"iteration":120,"passed_time":0.2295412048,"remaining_time":1.667493546},
{"learn":[5.15470988],"iteration":121,"passed_time":0.2301157504,"remaining_time":1.656078925},
{"learn":[5.146388143],"iteration":122,"passed_time":0.2307849082,"remaining_time":1.645515158},
{"learn":[5.139529364],"iteration":123,"passed_time":0.231411084,"remaining_time":1.634807335},
{"learn":[5.134276023],"iteration":124,"passed_time":0.2319794344,"remaining_time":1.623856041},
{"learn":[5.128536065],"iteration":125,"passed_time":0.2325602383,"remaining_time":1.613155938},
{"learn":[5.123300353],"iteration":126,"passed_time":0.2329782295,"remaining_time":1.601496018},
{"learn":[5.116200518],"iteration":127,"passed_time":0.2335517099,"remaining_time":1.591071024},
{"learn":[5.108728704],"iteration":128,"passed_time":0.2341077949,"remaining_time":1.580681313},
{"learn":[5.104075866],"iteration":129,"passed_time":0.2346481598,"remaining_time":1.570337685},
{"learn":[5.100317606],"iteration":130,"passed_time":0.2351573626,"remaining_time":1.559937009},
{"learn":[5.095814182],"iteration":131,"passed_time":0.2356869705,"remaining_time":1.549820382},
{"learn":[5.092146915],"iteration":132,"passed_time":0.2362635593,"remaining_time":1.54015418},
{"learn":[5.085258329],"iteration":133,"passed_time":0.2368586564,"remaining_time":1.530743257},
{"learn":[5.079219421],"iteration":134,"passed_time":0.2374462804,"remaining_time":1.521415056},
{"learn":[5.076476829],"iteration":135,"passed_time":0.2380000233,"remaining_time":1.512000148},
{"learn":[5.072133867],"iteration":136,"passed_time":0.2385600889,"remaining_time":1.502754429},
{"learn":[5.067031564],"iteration":137,"passed_time":0.2391166425,"remaining_time":1.493612651},
{"learn":[5.061358312],"iteration":138,"passed_time":0.2396691957,"remaining_time":1.484569622},
{"learn":[5.056759124],"iteration":139,"passed_time":0.2402437115,"remaining_time":1.475782799},
{"learn":[5.050254],"iteration":140,"passed_time":0.2408627848,"remaining_time":1.467383916},
{"learn":[5.048376474],"iteration":141,"passed_time":0.2412220639,"remaining_time":1.457524865},
{"learn":[5.042603751],"iteration":142,"passed_time":0.2417555616,"remaining_time":1.448842771},
{"learn":[5.037477349],"iteration":143,"passed_time":0.242371655,"remaining_time":1.440764838},
{"learn":[5.03230489],"iteration":144,"passed_time":0.2429737242,"remaining_time":1.432707132},
{"learn":[5.025976187],"iteration":145,"passed_time":0.2437622807,"remaining_time":1.425842382},
{"learn":[5.01952451],"iteration":146,"passed_time":0.244583547,"remaining_time":1.419250106},
{"learn":[5.017569424],"iteration":147,"passed_time":0.2454341601,"remaining_time":1.412904759},
{"learn":[5.008962367],"iteration":148,"passed_time":0.2462114564,"remaining_time":1.406214425},
{"learn":[5.003880266],"iteration":149,"passed_time":0.2468060408,"remaining_time":1.398567565},
{"learn":[4.996387564],"iteration":150,"passed_time":0.2473624565,"remaining_time":1.390799507},
{"learn":[4.993361683],"iteration":151,"passed_time":0.2478984217,"remaining_time":1.383012248},
{"learn":[4.99005752],"iteration":152,"passed_time":0.2484454172,"remaining_time":1.375380839},
{"learn":[4.986908764],"iteration":153,"passed_time":0.2490063135,"remaining_time":1.3679178},
{"learn":[4.985207175],"iteration":154,"passed_time":0.2495808549,"remaining_time":1.360618209},
{"learn":[4.979003494],"iteration":155,"passed_time":0.250169776,"remaining_time":1.353482634},
{"learn":[4.973142217],"iteration":156,"passed_time":0.250720255,"remaining_time":1.346224045},
{"learn":[4.967056696],"iteration":157,"passed_time":0.2512894568,"remaining_time":1.339150143},
{"learn":[4.961460696],"iteration":158,"passed_time":0.2518566856,"remaining_time":1.332147626},
{"learn":[4.954240363],"iteration":159,"passed_time":0.2524280147,"remaining_time":1.325247077},
{"learn":[4.952320707],"iteration":160,"passed_time":0.252788515,"remaining_time":1.317326485},
{"learn":[4.948337777],"iteration":161,"passed_time":0.2533686224,"remaining_time":1.310635219},
{"learn":[4.943228639],"iteration":162,"passed_time":0.2539328321,"remaining_time":1.303937303},
{"learn":[4.938545759],"iteration":163,"passed_time":0.2545177746,"remaining_time":1.297419875},
{"learn":[4.935330572],"iteration":164,"passed_time":0.2551228832,"remaining_time":1.291076409},
{"learn":[4.932051543],"iteration":165,"passed_time":0.2556685254,"remaining_time":1.284503314},
{"learn":[4.928964153],"iteration":166,"passed_time":0.2562173138,"remaining_time":1.278018098},
{"learn":[4.922860227],"iteration":167,"passed_time":0.2567817799,"remaining_time":1.271681196},
{"learn":[4.917668772],"iteration":168,"passed_time":0.2575197342,"remaining_time":1.266265675},
{"learn":[4.910365386],"iteration":169,"passed_time":0.259237213,"remaining_time":1.265687569},
{"learn":[4.906457206],"iteration":170,"passed_time":0.260296667,"remaining_time":1.261906064},
{"learn":[4.901996508],"iteration":171,"passed_time":0.2613382781,"remaining_time":1.258070315},
{"learn":[4.896816173],"iteration":172,"passed_time":0.26201351,"remaining_time":1.25251545},
{"learn":[4.891123132],"iteration":173,"passed_time":0.2626957276,"remaining_time":1.247049833},
{"learn":[4.887630202],"iteration":174,"passed_time":0.2633372841,"remaining_time":1.241447197},
{"learn":[4.885259712],"iteration":175,"passed_time":0.2639263481,"remaining_time":1.235655175},
{"learn":[4.880659728],"iteration":176,"passed_time":0.2645035787,"remaining_time":1.229866923},
{"learn":[4.877299723],"iteration":177,"passed_time":0.2650865062,"remaining_time":1.224163529},
{"learn":[4.874038772],"iteration":178,"passed_time":0.2656793604,"remaining_time":1.218562876},
{"learn":[4.86943698],"iteration":179,"passed_time":0.2662836267,"remaining_time":1.213069855},
{"learn":[4.861268711],"iteration":180,"passed_time":0.266884052,"remaining_time":1.207613473},
{"learn":[4.858673056],"iteration":181,"passed_time":0.2674805475,"remaining_time":1.20219279},
{"learn":[4.854036207],"iteration":182,"passed_time":0.2681243189,"remaining_time":1.197035894},
{"learn":[4.85130244],"iteration":183,"passed_time":0.2687199862,"remaining_time":1.191714721},
{"learn":[4.847510084],"iteration":184,"passed_time":0.2693338659,"remaining_time":1.186524869},
{"learn":[4.845691673],"iteration":185,"passed_time":0.2699263333,"remaining_time":1.181290512},
{"learn":[4.842058646],"iteration":186,"passed_time":0.2708823226,"remaining_time":1.177686247},
{"learn":[4.838623675],"iteration":187,"passed_time":0.2714940304,"remaining_time":1.172623152},
{"learn":[4.834602161],"iteration":188,"passed_time":0.2720648575,"remaining_time":1.167431743},
{"learn":[4.830858976],"iteration":189,"passed_time":0.2726969109,"remaining_time":1.162549988},
{"learn":[4.827590511],"iteration":190,"passed_time":0.2734549581,"remaining_time":1.158246393},
{"learn":[4.822246226],"iteration":191,"passed_time":0.2741019241,"remaining_time":1.153512264},
{"learn":[4.816686395],"iteration":192,"passed_time":0.2748103731,"remaining_time":1.149077571},
{"learn":[4.814797121],"iteration":193,"passed_time":0.2755746084,"remaining_time":1.144913064},
{"learn":[4.811639392],"iteration":194,"passed_time":0.2762557683,"remaining_time":1.14044048},
{"learn":[4.804813432],"iteration":195,"passed_time":0.2771316674,"remaining_time":1.136805411},
{"learn":[4.80251613],"iteration":196,"passed_time":0.2777556052,"remaining_time":1.132171325},
{"learn":[4.800087884],"iteration":197,"passed_time":0.2783350173,"remaining_time":1.127397393},
{"learn":[4.794773135],"iteration":198,"passed_time":0.2788696016,"remaining_time":1.12248518},
{"learn":[4.791664833],"iteration":199,"passed_time":0.2793926136,"remaining_time":1.117570454},
{"learn":[4.785989873],"iteration":200,"passed_time":0.2799181901,"remaining_time":1.112709621},
{"learn":[4.782387142],"iteration":201,"passed_time":0.2804398967,"remaining_time":1.107876423},
{"learn":[4.778623704],"iteration":202,"passed_time":0.2811172535,"remaining_time":1.103696803},
{"learn":[4.775772178],"iteration":203,"passed_time":0.2816411716,"remaining_time":1.098952807},
{"learn":[4.77023101],"iteration":204,"passed_time":0.2821815551,"remaining_time":1.094313835},
{"learn":[4.764496689],"iteration":205,"passed_time":0.2826916715,"remaining_time":1.089597996},
{"learn":[4.763138716],"iteration":206,"passed_time":0.2832215949,"remaining_time":1.08499867},
{"learn":[4.758053283],"iteration":207,"passed_time":0.2838125616,"remaining_time":1.080670907},
{"learn":[4.755063788],"iteration":208,"passed_time":0.2846049906,"remaining_time":1.077141376},
{"learn":[4.752465267],"iteration":209,"passed_time":0.2853040268,"remaining_time":1.073286577},
{"learn":[4.748067377],"iteration":210,"passed_time":0.2859860781,"remaining_time":1.069398178},
{"learn":[4.744163298],"iteration":211,"passed_time":0.2866127608,"remaining_time":1.065334224},
{"learn":[4.736670896],"iteration":212,"passed_time":0.2872013429,"remaining_time":1.061161769},
{"learn":[4.73349255],"iteration":213,"passed_time":0.2877649148,"remaining_time":1.056930949},
{"learn":[4.731864595],"iteration":214,"passed_time":0.28856787,"remaining_time":1.053608269},
{"learn":[4.728398311],"iteration":215,"passed_time":0.2895061054,"remaining_time":1.050799938},
{"learn":[4.723865975],"iteration":216,"passed_time":0.2905802,"remaining_time":1.048499063},
{"learn":[4.723483365],"iteration":217,"passed_time":0.2911726418,"remaining_time":1.044481678},
{"learn":[4.72095416],"iteration":218,"passed_time":0.29172852,"remaining_time":1.040365179},
{"learn":[4.716173382],"iteration":219,"passed_time":0.2922791088,"remaining_time":1.036262295},
{"learn":[4.710563974],"iteration":220,"passed_time":0.2928439803,"remaining_time":1.032241903},
{"learn":[4.707160263],"iteration":221,"passed_time":0.2934098509,"remaining_time":1.028256144},
{"learn":[4.70408351],"iteration":222,"passed_time":0.2939694851,"remaining_time":1.024279327},
{"learn":[4.702501831],"iteration":223,"passed_time":0.294540758,"remaining_time":1.02037334},
{"learn":[4.700269738],"iteration":224,"passed_time":0.2950929669,"remaining_time":1.01643133},
{"learn":[4.695346302],"iteration":225,"passed_time":0.2956507999,"remaining_time":1.01253858},
{"learn":[4.689769299],"iteration":226,"passed_time":0.2962169388,"remaining_time":1.008703496},
{"learn":[4.687919514],"iteration":227,"passed_time":0.2967728359,"remaining_time":1.004862409},
{"learn":[4.682982074],"iteration":228,"passed_time":0.2973270132,"remaining_time":1.001044223},
{"learn":[4.679578702],"iteration":229,"passed_time":0.2978918896,"remaining_time":0.9972902392},
{"learn":[4.675751423],"iteration":230,"passed_time":0.2984515572,"remaining_time":0.9935465261},
{"learn":[4.672710726],"iteration":231,"passed_time":0.2992504872,"remaining_time":0.9906223026},
{"learn":[4.6690533],"iteration":232,"passed_time":0.2998277084,"remaining_time":0.9869864908},
{"learn":[4.667595702],"iteration":233,"passed_time":0.3003608337,"remaining_time":0.9832324728},
{"learn":[4.664241291],"iteration":234,"passed_time":0.3008865754,"remaining_time":0.9794818305},
{"learn":[4.662246999],"iteration":235,"passed_time":0.3014310488,"remaining_time":0.9758191581},
{"learn":[4.658668443],"iteration":236,"passed_time":0.3019490791,"remaining_time":0.9720976681},
{"learn":[4.658017572],"iteration":237,"passed_time":0.3024619554,"remaining_time":0.9683865967},
{"learn":[4.657656705],"iteration":238,"passed_time":0.3029692699,"remaining_time":0.9646845792},
{"learn":[4.653242871],"iteration":239,"passed_time":0.3037255572,"remaining_time":0.9617975979},
{"learn":[4.6507302],"iteration":240,"passed_time":0.3043886484,"remaining_time":0.9586347888},
{"learn":[4.647671336],"iteration":241,"passed_time":0.3051214541,"remaining_time":0.955711001},
{"learn":[4.645506007],"iteration":242,"passed_time":0.3058974583,"remaining_time":0.9529398186},
{"learn":[4.641297906],"iteration":243,"passed_time":0.3064690496,"remaining_time":0.9495516454},
{"learn":[4.63798107],"iteration":244,"passed_time":0.3070801001,"remaining_time":0.9463080636},
{"learn":[4.635062318],"iteration":245,"passed_time":0.307820882,"remaining_time":0.9434835163},
{"learn":[4.631606017],"iteration":246,"passed_time":0.3085518936,"remaining_time":0.9406460561},
{"learn":[4.630215494],"iteration":247,"passed_time":0.3090832049,"remaining_time":0.9372200405},
{"learn":[4.62729814],"iteration":248,"passed_time":0.3096561379,"remaining_time":0.9339428094},
{"learn":[4.624691756],"iteration":249,"passed_time":0.3101891835,"remaining_time":0.9305675505},
{"learn":[4.621840053],"iteration":250,"passed_time":0.3107240712,"remaining_time":0.9272204356},
{"learn":[4.619602091],"iteration":251,"passed_time":0.3112650285,"remaining_time":0.9239136561},
{"learn":[4.613584029],"iteration":252,"passed_time":0.3117925565,"remaining_time":0.9205890899},
{"learn":[4.6119388],"iteration":253,"passed_time":0.3124688074,"remaining_time":0.9177233476},
{"learn":[4.60870702],"iteration":254,"passed_time":0.3130239503,"remaining_time":0.9145209527},
{"learn":[4.604771557],"iteration":255,"passed_time":0.3135487676,"remaining_time":0.9112511057},
{"learn":[4.604231277],"iteration":256,"passed_time":0.3140958246,"remaining_time":0.908066917},
{"learn":[4.600750354],"iteration":257,"passed_time":0.3146421748,"remaining_time":0.9049011384},
{"learn":[4.596488253],"iteration":258,"passed_time":0.3151701466,"remaining_time":0.9017030064},
{"learn":[4.59470784],"iteration":259,"passed_time":0.3156961195,"remaining_time":0.8985197247},
{"learn":[4.588818005],"iteration":260,"passed_time":0.3162447738,"remaining_time":0.8954210261},
{"learn":[4.585054174],"iteration":261,"passed_time":0.3167735981,"remaining_time":0.8922859367},
{"learn":[4.581471435],"iteration":262,"passed_time":0.3174176577,"remaining_time":0.8894935883},
{"learn":[4.577555199],"iteration":263,"passed_time":0.3180168366,"remaining_time":0.886592393},
{"learn":[4.57457145],"iteration":264,"passed_time":0.3187545709,"remaining_time":0.8840928665},
{"learn":[4.573029224],"iteration":265,"passed_time":0.3193554495,"remaining_time":0.8812289471},
{"learn":[4.571326203],"iteration":266,"passed_time":0.320014392,"remaining_time":0.8785413832},
{"learn":[4.571019224],"iteration":267,"passed_time":0.320613589,"remaining_time":0.8757057731},
{"learn":[4.565766631],"iteration":268,"passed_time":0.3212829834,"remaining_time":0.8730775497},
{"learn":[4.563383471],"iteration":269,"passed_time":0.3220974007,"remaining_time":0.8708559352},
{"learn":[4.558165805],"iteration":270,"passed_time":0.3228726609,"remaining_time":0.8685393719},
{"learn":[4.55629209],"iteration":271,"passed_time":0.3235273346,"remaining_time":0.8659113956},
{"learn":[4.549383848],"iteration":272,"passed_time":0.3241302419,"remaining_time":0.8631600214},
{"learn":[4.546227503],"iteration":273,"passed_time":0.3247211673,"remaining_time":0.8603925819},
{"learn":[4.540620977],"iteration":274,"passed_time":0.3253102077,"remaining_time":0.857636002},
{"learn":[4.532898237],"iteration":275,"passed_time":0.3259325184,"remaining_time":0.8549824034},
{"learn":[4.529757367],"iteration":276,"passed_time":0.3267399855,"remaining_time":0.8528267493},
{"learn":[4.52579294],"iteration":277,"passed_time":0.3274014315,"remaining_time":0.8503015595},
{"learn":[4.521572155],"iteration":278,"passed_time":0.3280366728,"remaining_time":0.8477220111},
{"learn":[4.518818099],"iteration":279,"passed_time":0.3286652996,"remaining_time":0.8451393419},
{"learn":[4.514012334],"iteration":280,"passed_time":0.3292674275,"remaining_time":0.842502777},
{"learn":[4.508331416],"iteration":281,"passed_time":0.3298544495,"remaining_time":0.8398421798},
{"learn":[4.506038537],"iteration":282,"passed_time":0.3304235633,"remaining_time":0.8371508653},
{"learn":[4.505805643],"iteration":283,"passed_time":0.3309861501,"remaining_time":0.8344580404},
{"learn":[4.501550352],"iteration":284,"passed_time":0.3315649814,"remaining_time":0.8318209182},
{"learn":[4.494692643],"iteration":285,"passed_time":0.3321467343,"remaining_time":0.8292054835},
{"learn":[4.489330245],"iteration":286,"passed_time":0.332740311,"remaining_time":0.8266335949},
{"learn":[4.484826955],"iteration":287,"passed_time":0.3334851539,"remaining_time":0.8244494084},
{"learn":[4.478285428],"iteration":288,"passed_time":0.334289081,"remaining_time":0.8224205417},
{"learn":[4.475311671],"iteration":289,"passed_time":0.3349801758,"remaining_time":0.8201238788},
{"learn":[4.471581298],"iteration":290,"passed_time":0.3357367389,"remaining_time":0.8179977591},
{"learn":[4.469164956],"iteration":291,"passed_time":0.3363835819,"remaining_time":0.8156149862},
{"learn":[4.462068024],"iteration":292,"passed_time":0.3369818678,"remaining_time":0.8131268961},
{"learn":[4.458540976],"iteration":293,"passed_time":0.3375441318,"remaining_time":0.8105651601},
{"learn":[4.455757458],"iteration":294,"passed_time":0.3381282239,"remaining_time":0.8080691453},
{"learn":[4.453027414],"iteration":295,"passed_time":0.3387171838,"remaining_time":0.8055976263},
{"learn":[4.450659338],"iteration":296,"passed_time":0.3392989272,"remaining_time":0.8031217031},
{"learn":[4.444696901],"iteration":297,"passed_time":0.339886327,"remaining_time":0.8006718172},
{"learn":[4.442052813],"iteration":298,"passed_time":0.3406875474,"remaining_time":0.798735688},
{"learn":[4.440036756],"iteration":299,"passed_time":0.3412703027,"remaining_time":0.796297373},
{"learn":[4.435017051],"iteration":300,"passed_time":0.3418323037,"remaining_time":0.7938231903},
{"learn":[4.429962125],"iteration":301,"passed_time":0.3423964911,"remaining_time":0.7913667245},
{"learn":[4.427666256],"iteration":302,"passed_time":0.3429538398,"remaining_time":0.7889070177},
{"learn":[4.425030004],"iteration":303,"passed_time":0.3435300268,"remaining_time":0.7865029562},
{"learn":[4.422588771],"iteration":304,"passed_time":0.3441844727,"remaining_time":0.7842892082},
{"learn":[4.418936667],"iteration":305,"passed_time":0.345092302,"remaining_time":0.782660319},
{"learn":[4.416887976],"iteration":306,"passed_time":0.3457614561,"remaining_time":0.7804973586},
{"learn":[4.413773354],"iteration":307,"passed_time":0.3463845187,"remaining_time":0.778240542},
{"learn":[4.411129391],"iteration":308,"passed_time":0.3469609604,"remaining_time":0.7758900442},
{"learn":[4.40850819],"iteration":309,"passed_time":0.3475198688,"remaining_time":0.7735119661},
{"learn":[4.404880292],"iteration":310,"passed_time":0.3480995295,"remaining_time":0.7711915621},
{"learn":[4.404593827],"iteration":311,"passed_time":0.3490423215,"remaining_time":0.7696830679},
{"learn":[4.402139942],"iteration":312,"passed_time":0.3497407715,"remaining_time":0.7676418851},
{"learn":[4.400284725],"iteration":313,"passed_time":0.3505354559,"remaining_time":0.7658194992},
{"learn":[4.395805521],"iteration":314,"passed_time":0.3513751637,"remaining_time":0.7641015466},
{"learn":[4.392838833],"iteration":315,"passed_time":0.3519564064,"remaining_time":0.7618296898},
{"learn":[4.389213061],"iteration":316,"passed_time":0.3525862143,"remaining_time":0.7596731369},
{"learn":[4.3861981],"iteration":317,"passed_time":0.3533025363,"remaining_time":0.7577117287},
{"learn":[4.385054234],"iteration":318,"passed_time":0.3539090906,"remaining_time":0.7555237952},
{"learn":[4.379364607],"iteration":319,"passed_time":0.354646888,"remaining_time":0.753624637},
{"learn":[4.378387619],"iteration":320,"passed_time":0.3552747998,"remaining_time":0.7515002774},
{"learn":[4.375816727],"iteration":321,"passed_time":0.3559032779,"remaining_time":0.7493864051},
{"learn":[4.374600202],"iteration":322,"passed_time":0.3564780076,"remaining_time":0.7471690748},
{"learn":[4.37098897],"iteration":323,"passed_time":0.3570735292,"remaining_time":0.7450052646},
{"learn":[4.367418484],"iteration":324,"passed_time":0.3576648398,"remaining_time":0.7428423596},
{"learn":[4.363584638],"iteration":325,"passed_time":0.358257391,"remaining_time":0.7406916611},
{"learn":[4.360770706],"iteration":326,"passed_time":0.3588456317,"remaining_time":0.7385416212},
{"learn":[4.358675808],"iteration":327,"passed_time":0.3594228496,"remaining_time":0.736378521},
{"learn":[4.354228195],"iteration":328,"passed_time":0.3600209084,"remaining_time":0.734267567},
{"learn":[4.353773425],"iteration":329,"passed_time":0.3606168284,"remaining_time":0.7321614394},
{"learn":[4.351648009],"iteration":330,"passed_time":0.3612239706,"remaining_time":0.7300871188},
{"learn":[4.348209927],"iteration":331,"passed_time":0.3618460051,"remaining_time":0.7280516007},
{"learn":[4.345852733],"iteration":332,"passed_time":0.3626107516,"remaining_time":0.7263104243},
{"learn":[4.34237339],"iteration":333,"passed_time":0.3631769652,"remaining_time":0.724179218},
{"learn":[4.340814362],"iteration":334,"passed_time":0.3640005248,"remaining_time":0.7225682059},
{"learn":[4.339707068],"iteration":335,"passed_time":0.3647182817,"remaining_time":0.7207527949},
{"learn":[4.335430786],"iteration":336,"passed_time":0.3653517912,"remaining_time":0.718778153},
{"learn":[4.33521887],"iteration":337,"passed_time":0.365943245,"remaining_time":0.7167290776},
{"learn":[4.328507238],"iteration":338,"passed_time":0.3664973728,"remaining_time":0.7146158213},
{"learn":[4.326140732],"iteration":339,"passed_time":0.3670331452,"remaining_time":0.7124761054},
{"learn":[4.323785636],"iteration":340,"passed_time":0.3675793311,"remaining_time":0.7103659215},
{"learn":[4.320632534],"iteration":341,"passed_time":0.3681105966,"remaining_time":0.7082361771},
{"learn":[4.31973724],"iteration":342,"passed_time":0.3687266896,"remaining_time":0.7062782363},
{"learn":[4.318000924],"iteration":343,"passed_time":0.369519446,"remaining_time":0.70466499},
{"learn":[4.312713628],"iteration":344,"passed_time":0.3701728762,"remaining_time":0.7027919823},
{"learn":[4.308220789],"iteration":345,"passed_time":0.3713656082,"remaining_time":0.7019453982},
{"learn":[4.305890947],"iteration":346,"passed_time":0.3723370427,"remaining_time":0.7006803714},
{"learn":[4.305137856],"iteration":347,"passed_time":0.3730374657,"remaining_time":0.6989092748},
{"learn":[4.304787172],"iteration":348,"passed_time":0.3738804057,"remaining_time":0.697410155},
{"learn":[4.30350134],"iteration":349,"passed_time":0.3746099154,"remaining_time":0.6957041285},
{"learn":[4.30293809],"iteration":350,"passed_time":0.3752571072,"remaining_time":0.6938514603},
{"learn":[4.299548459],"iteration":351,"passed_time":0.3759432253,"remaining_time":0.6920773011},
{"learn":[4.294768408],"iteration":352,"passed_time":0.3765971233,"remaining_time":0.6902502514},
{"learn":[4.294581479],"iteration":353,"passed_time":0.3774551629,"remaining_time":0.6888023594},
{"learn":[4.292551604],"iteration":354,"passed_time":0.3780128984,"remaining_time":0.6868121676},
{"learn":[4.288628894],"iteration":355,"passed_time":0.3788188244,"remaining_time":0.685278997},
{"learn":[4.287802767],"iteration":356,"passed_time":0.379523067,"remaining_time":0.6835667566},
{"learn":[4.284566905],"iteration":357,"passed_time":0.3803446851,"remaining_time":0.6820706363},
{"learn":[4.27890232],"iteration":358,"passed_time":0.3809898725,"remaining_time":0.6802632543},
{"learn":[4.276938023],"iteration":359,"passed_time":0.3815899816,"remaining_time":0.6783821895},
{"learn":[4.273425094],"iteration":360,"passed_time":0.3821542214,"remaining_time":0.6764447299},
{"learn":[4.269726505],"iteration":361,"passed_time":0.3827717952,"remaining_time":0.6746088546},
{"learn":[4.265565857],"iteration":362,"passed_time":0.3833712735,"remaining_time":0.6727479372},
{"learn":[4.262117173],"iteration":363,"passed_time":0.384213292,"remaining_time":0.67131773},
{"learn":[4.259185148],"iteration":364,"passed_time":0.3849698811,"remaining_time":0.6697421219},
{"learn":[4.257668507],"iteration":365,"passed_time":0.3855433161,"remaining_time":0.6678537225},
{"learn":[4.253432436],"iteration":366,"passed_time":0.3862264267,"remaining_time":0.6661616569},
{"learn":[4.250216667],"iteration":367,"passed_time":0.386803934,"remaining_time":0.6642937127},
{"learn":[4.24514828],"iteration":368,"passed_time":0.3873632358,"remaining_time":0.6624016309},
{"learn":[4.244015772],"iteration":369,"passed_time":0.3878998893,"remaining_time":0.6604781898},
{"learn":[4.240329192],"iteration":370,"passed_time":0.3884879322,"remaining_time":0.6586493514},
{"learn":[4.236718014],"iteration":371,"passed_time":0.3890358917,"remaining_time":0.6567595161},
{"learn":[4.233495944],"iteration":372,"passed_time":0.3896173775,"remaining_time":0.6549332325},
{"learn":[4.230357491],"iteration":373,"passed_time":0.3902470624,"remaining_time":0.653194281},
{"learn":[4.227381215],"iteration":374,"passed_time":0.3909354177,"remaining_time":0.6515590295},
{"learn":[4.226169067],"iteration":375,"passed_time":0.3914908269,"remaining_time":0.6497081808},
{"learn":[4.225963861],"iteration":376,"passed_time":0.3919919971,"remaining_time":0.6477745735},
{"learn":[4.224346548],"iteration":377,"passed_time":0.3925139853,"remaining_time":0.6458828011},
{"learn":[4.222595381],"iteration":378,"passed_time":0.3930313533,"remaining_time":0.643990687},
{"learn":[4.219700938],"iteration":379,"passed_time":0.3937867753,"remaining_time":0.6424942123},
{"learn":[4.216356207],"iteration":380,"passed_time":0.3945972111,"remaining_time":0.6410910071},
{"learn":[4.214326494],"iteration":381,"passed_time":0.3954037246,"remaining_time":0.6396845597},
{"learn":[4.212901398],"iteration":382,"passed_time":0.3961377429,"remaining_time":0.6381644579},
{"learn":[4.211331091],"iteration":383,"passed_time":0.3967270656,"remaining_time":0.6364163345},
{"learn":[4.208624791],"iteration":384,"passed_time":0.3973011819,"remaining_time":0.6346499399},
{"learn":[4.204659106],"iteration":385,"passed_time":0.3979196557,"remaining_time":0.6329602813},
{"learn":[4.202968852],"iteration":386,"passed_time":0.3984965152,"remaining_time":0.6312102425},
{"learn":[4.197261935],"iteration":387,"passed_time":0.3991085867,"remaining_time":0.6295217914},
{"learn":[4.196934403],"iteration":388,"passed_time":0.3998043591,"remaining_time":0.6279703429},
{"learn":[4.192479929],"iteration":389,"passed_time":0.4004520971,"remaining_time":0.6263481519},
{"learn":[4.190243116],"iteration":390,"passed_time":0.401064067,"remaining_time":0.6246752348},
{"learn":[4.185852431],"iteration":391,"passed_time":0.4016354606,"remaining_time":0.622944796},
{"learn":[4.180967944],"iteration":392,"passed_time":0.4022103603,"remaining_time":0.6212256711},
{"learn":[4.178283162],"iteration":393,"passed_time":0.4027785837,"remaining_time":0.6195020855},
{"learn":[4.176341157],"iteration":394,"passed_time":0.4033320864,"remaining_time":0.6177618032},
{"learn":[4.176041504],"iteration":395,"passed_time":0.4038914084,"remaining_time":0.6160363907},
{"learn":[4.175564513],"iteration":396,"passed_time":0.4044286056,"remaining_time":0.6142832473},
{"learn":[4.170830274],"iteration":397,"passed_time":0.4050233675,"remaining_time":0.6126232846},
{"learn":[4.167804808],"iteration":398,"passed_time":0.4055866145,"remaining_time":0.6109211912},
{"learn":[4.165860548],"iteration":399,"passed_time":0.406142188,"remaining_time":0.609213282},
{"learn":[4.160950571],"iteration":400,"passed_time":0.4067643997,"remaining_time":0.6076106618},
{"learn":[4.158544115],"iteration":401,"passed_time":0.4150529146,"remaining_time":0.6174170221},
{"learn":[4.154448767],"iteration":402,"passed_time":0.4156293637,"remaining_time":0.6157090078},
{"learn":[4.15197457],"iteration":403,"passed_time":0.4163128062,"remaining_time":0.6141644369},
{"learn":[4.149562679],"iteration":404,"passed_time":0.4168711338,"remaining_time":0.6124403076},
{"learn":[4.149327961],"iteration":405,"passed_time":0.4174542482,"remaining_time":0.6107581858},
{"learn":[4.147444889],"iteration":406,"passed_time":0.417986109,"remaining_time":0.6090067878},
{"learn":[4.147254809],"iteration":407,"passed_time":0.4184831253,"remaining_time":0.6072108092},
{"learn":[4.144589165],"iteration":408,"passed_time":0.4190104052,"remaining_time":0.6054649131},
{"learn":[4.141691034],"iteration":409,"passed_time":0.4195303815,"remaining_time":0.6037144514},
{"learn":[4.138893468],"iteration":410,"passed_time":0.4200636455,"remaining_time":0.60198902},
{"learn":[4.136964597],"iteration":411,"passed_time":0.4205961995,"remaining_time":0.6002683624},
{"learn":[4.133773523],"iteration":412,"passed_time":0.421129788,"remaining_time":0.5985549287},
{"learn":[4.131363444],"iteration":413,"passed_time":0.4216459646,"remaining_time":0.5968225489},
{"learn":[4.130228592],"iteration":414,"passed_time":0.4221553689,"remaining_time":0.5950864839},
{"learn":[4.12884186],"iteration":415,"passed_time":0.4228040189,"remaining_time":0.5935517957},
{"learn":[4.12413494],"iteration":416,"passed_time":0.4233314094,"remaining_time":0.5918518266},
{"learn":[4.119422508],"iteration":417,"passed_time":0.4239016544,"remaining_time":0.590217136},
{"learn":[4.117038244],"iteration":418,"passed_time":0.4251933789,"remaining_time":0.589587955},
{"learn":[4.116067631],"iteration":419,"passed_time":0.4262406245,"remaining_time":0.5886180052},
{"learn":[4.110343455],"iteration":420,"passed_time":0.4272391012,"remaining_time":0.5875806166},
{"learn":[4.105604544],"iteration":421,"passed_time":0.4278376038,"remaining_time":0.5859955806},
{"learn":[4.103390131],"iteration":422,"passed_time":0.4284652485,"remaining_time":0.5844549607},
{"learn":[4.096724402],"iteration":423,"passed_time":0.42912448,"remaining_time":0.5829615577},
{"learn":[4.093431279],"iteration":424,"passed_time":0.4297529189,"remaining_time":0.5814304197},
{"learn":[4.091412744],"iteration":425,"passed_time":0.4303456398,"remaining_time":0.5798553926},
{"learn":[4.091192901],"iteration":426,"passed_time":0.4309100027,"remaining_time":0.5782469122},
{"learn":[4.088994581],"iteration":427,"passed_time":0.431518553,"remaining_time":0.5767023653},
{"learn":[4.087845355],"iteration":428,"passed_time":0.4321181002,"remaining_time":0.5751501986},
{"learn":[4.083650279],"iteration":429,"passed_time":0.4327123622,"remaining_time":0.5735954569},
{"learn":[4.079840652],"iteration":430,"passed_time":0.433321659,"remaining_time":0.5720650208},
{"learn":[4.075707828],"iteration":431,"passed_time":0.4339103509,"remaining_time":0.5705117577},
{"learn":[4.071345409],"iteration":432,"passed_time":0.4345648195,"remaining_time":0.5690490823},
{"learn":[4.067460475],"iteration":433,"passed_time":0.435247466,"remaining_time":0.5676268796},
{"learn":[4.064914749],"iteration":434,"passed_time":0.4361489719,"remaining_time":0.5664923428},
{"learn":[4.063823175],"iteration":435,"passed_time":0.4369888635,"remaining_time":0.565279172},
{"learn":[4.058898471],"iteration":436,"passed_time":0.4376046534,"remaining_time":0.5637789929},
{"learn":[4.054120355],"iteration":437,"passed_time":0.4381658944,"remaining_time":0.56221286},
{"learn":[4.052715901],"iteration":438,"passed_time":0.4387048994,"remaining_time":0.5606228897},
{"learn":[4.052114167],"iteration":439,"passed_time":0.439247743,"remaining_time":0.5590425819},
{"learn":[4.051377267],"iteration":440,"passed_time":0.4399974744,"remaining_time":0.5577292249},
{"learn":[4.049275336],"iteration":441,"passed_time":0.4407025707,"remaining_time":0.5563620689},
{"learn":[4.047099198],"iteration":442,"passed_time":0.4413856875,"remaining_time":0.5549702662},
{"learn":[4.044348685],"iteration":443,"passed_time":0.4420553874,"remaining_time":0.5535648544},
{"learn":[4.042822379],"iteration":444,"passed_time":0.4427740018,"remaining_time":0.552223755},
{"learn":[4.041258611],"iteration":445,"passed_time":0.4433856633,"remaining_time":0.5507525952},
{"learn":[4.040044254],"iteration":446,"passed_time":0.444050999,"remaining_time":0.5493516834},
{"learn":[4.036860137],"iteration":447,"passed_time":0.4446869711,"remaining_time":0.5479178751},
{"learn":[4.036372284],"iteration":448,"passed_time":0.445262834,"remaining_time":0.5464138565},
{"learn":[4.03368231],"iteration":449,"passed_time":0.4461943893,"remaining_time":0.5453486981},
{"learn":[4.032439519],"iteration":450,"passed_time":0.4468913606,"remaining_time":0.5439985742},
{"learn":[4.032008634],"iteration":451,"passed_time":0.4475593847,"remaining_time":0.5426162452},
{"learn":[4.030034932],"iteration":452,"passed_time":0.448401691,"remaining_time":0.5414475165},
{"learn":[4.028173412],"iteration":453,"passed_time":0.4491294911,"remaining_time":0.5401425158},
{"learn":[4.023806097],"iteration":454,"passed_time":0.4503062,"remaining_time":0.5393777561},
{"learn":[4.020239186],"iteration":455,"passed_time":0.4513581375,"remaining_time":0.5384623394},
{"learn":[4.017384838],"iteration":456,"passed_time":0.4519399573,"remaining_time":0.5369877392},
{"learn":[4.016468229],"iteration":457,"passed_time":0.4524835617,"remaining_time":0.5354718132},
{"learn":[4.014530169],"iteration":458,"passed_time":0.4530422484,"remaining_time":0.5339779007},
{"learn":[4.012884822],"iteration":459,"passed_time":0.4536065114,"remaining_time":0.5324946003},
{"learn":[4.008924707],"iteration":460,"passed_time":0.4549523522,"remaining_time":0.531929106},
{"learn":[4.008286778],"iteration":461,"passed_time":0.4558714811,"remaining_time":0.5308633264},
{"learn":[4.006444202],"iteration":462,"passed_time":0.456728264,"remaining_time":0.5297258699},
{"learn":[4.003284363],"iteration":463,"passed_time":0.4574149811,"remaining_time":0.5283931679},
{"learn":[3.999811484],"iteration":464,"passed_time":0.4581609338,"remaining_time":0.527131397},
{"learn":[3.997483319],"iteration":465,"passed_time":0.4588177101,"remaining_time":0.5257696507},
{"learn":[3.99708333],"iteration":466,"passed_time":0.4594106382,"remaining_time":0.5243380518},
{"learn":[3.995860263],"iteration":467,"passed_time":0.4600168177,"remaining_time":0.5229251004},
{"learn":[3.994131111],"iteration":468,"passed_time":0.4606295311,"remaining_time":0.5215229873},
{"learn":[3.993125499],"iteration":469,"passed_time":0.4614905886,"remaining_time":0.5204042808},
{"learn":[3.992954084],"iteration":470,"passed_time":0.4623978632,"remaining_time":0.5193385767},
{"learn":[3.990635743],"iteration":471,"passed_time":0.4631595124,"remaining_time":0.518110641},
{"learn":[3.986678254],"iteration":472,"passed_time":0.4644260128,"remaining_time":0.5174471644},
{"learn":[3.986393291],"iteration":473,"passed_time":0.4657387047,"remaining_time":0.5168324023},
{"learn":[3.986152671],"iteration":474,"passed_time":0.4663719945,"remaining_time":0.5154637834},
{"learn":[3.985596662],"iteration":475,"passed_time":0.4669199462,"remaining_time":0.5140043105},
{"learn":[3.983853457],"iteration":476,"passed_time":0.4675196552,"remaining_time":0.5126054081},
{"learn":[3.983263928],"iteration":477,"passed_time":0.4680836469,"remaining_time":0.5111708445},
{"learn":[3.980067202],"iteration":478,"passed_time":0.4686804218,"remaining_time":0.5097755736},
{"learn":[3.978115407],"iteration":479,"passed_time":0.469695593,"remaining_time":0.5088368924},
{"learn":[3.972661644],"iteration":480,"passed_time":0.4703111084,"remaining_time":0.5074666637},
{"learn":[3.969938254],"iteration":481,"passed_time":0.4709473566,"remaining_time":0.506121848},
{"learn":[3.968211434],"iteration":482,"passed_time":0.4716632508,"remaining_time":0.5048652188},
{"learn":[3.966113368],"iteration":483,"passed_time":0.4723119252,"remaining_time":0.5035391599},
{"learn":[3.962246044],"iteration":484,"passed_time":0.4735932267,"remaining_time":0.5028876531},
{"learn":[3.961319703],"iteration":485,"passed_time":0.4742796891,"remaining_time":0.5016044449},
{"learn":[3.96078191],"iteration":486,"passed_time":0.4748576167,"remaining_time":0.500209358},
{"learn":[3.958913633],"iteration":487,"passed_time":0.4754815883,"remaining_time":0.4988659287},
{"learn":[3.957428286],"iteration":488,"passed_time":0.4760673817,"remaining_time":0.4974855461},
{"learn":[3.952641965],"iteration":489,"passed_time":0.4766633173,"remaining_time":0.4961189629},
{"learn":[3.951486786],"iteration":490,"passed_time":0.4774757166,"remaining_time":0.4949799181},
{"learn":[3.94938344],"iteration":491,"passed_time":0.4782646683,"remaining_time":0.4938179908},
{"learn":[3.947297924],"iteration":492,"passed_time":0.4789398973,"remaining_time":0.4925406246},
{"learn":[3.946284886],"iteration":493,"passed_time":0.4795685658,"remaining_time":0.4912180047},
{"learn":[3.943288204],"iteration":494,"passed_time":0.4808296316,"remaining_time":0.4905433615},
{"learn":[3.943076488],"iteration":495,"passed_time":0.4817065739,"remaining_time":0.4894760348},
{"learn":[3.942347078],"iteration":496,"passed_time":0.4823106834,"remaining_time":0.4881333476},
{"learn":[3.940251541],"iteration":497,"passed_time":0.4828951747,"remaining_time":0.4867738508},
{"learn":[3.939011019],"iteration":498,"passed_time":0.4834594281,"remaining_time":0.4853971413},
{"learn":[3.938760512],"iteration":499,"passed_time":0.483994469,"remaining_time":0.483994469},
{"learn":[3.934522727],"iteration":500,"passed_time":0.4847943655,"remaining_time":0.4828590586},
{"learn":[3.930091193],"iteration":501,"passed_time":0.4854095312,"remaining_time":0.4815417262},
{"learn":[3.927671752],"iteration":502,"passed_time":0.4861080432,"remaining_time":0.4803095377},
{"learn":[3.927280041],"iteration":503,"passed_time":0.4869070987,"remaining_time":0.4791784146},
{"learn":[3.925987561],"iteration":504,"passed_time":0.4874877733,"remaining_time":0.47783455},
{"learn":[3.921645957],"iteration":505,"passed_time":0.4881234708,"remaining_time":0.4765474201},
{"learn":[3.920333743],"iteration":506,"passed_time":0.4886929933,"remaining_time":0.4751985123},
{"learn":[3.918659461],"iteration":507,"passed_time":0.4893517608,"remaining_time":0.4739391069},
{"learn":[3.916124385],"iteration":508,"passed_time":0.4899662672,"remaining_time":0.4726393658},
{"learn":[3.913849268],"iteration":509,"passed_time":0.4905629633,"remaining_time":0.4713252},
{"learn":[3.912826119],"iteration":510,"passed_time":0.4911594179,"remaining_time":0.4700136112},
{"learn":[3.910034145],"iteration":511,"passed_time":0.491878273,"remaining_time":0.4688214789},
{"learn":[3.90792379],"iteration":512,"passed_time":0.4936199673,"remaining_time":0.4686021912},
{"learn":[3.907823851],"iteration":513,"passed_time":0.4948425328,"remaining_time":0.4678861303},
{"learn":[3.904527401],"iteration":514,"passed_time":0.4958112722,"remaining_time":0.4669290622},
{"learn":[3.903378283],"iteration":515,"passed_time":0.4964785116,"remaining_time":0.4656891465},
{"learn":[3.902170135],"iteration":516,"passed_time":0.4970561526,"remaining_time":0.4643677403},
{"learn":[3.899435429],"iteration":517,"passed_time":0.4976317794,"remaining_time":0.4630473314},
{"learn":[3.897497505],"iteration":518,"passed_time":0.4982791624,"remaining_time":0.461796295},
{"learn":[3.896426119],"iteration":519,"passed_time":0.4989135834,"remaining_time":0.4605356154},
{"learn":[3.896044669],"iteration":520,"passed_time":0.4998410322,"remaining_time":0.4595467455},
{"learn":[3.892795942],"iteration":521,"passed_time":0.5006585796,"remaining_time":0.4584574733},
{"learn":[3.892413888],"iteration":522,"passed_time":0.5013827835,"remaining_time":0.4572841065},
{"learn":[3.891738985],"iteration":523,"passed_time":0.5020488404,"remaining_time":0.4560596337},
{"learn":[3.88822057],"iteration":524,"passed_time":0.5028090836,"remaining_time":0.4549225042},
{"learn":[3.883837053],"iteration":525,"passed_time":0.5034975004,"remaining_time":0.4537220821},
{"learn":[3.881769742],"iteration":526,"passed_time":0.5041958579,"remaining_time":0.4525325252},
{"learn":[3.880356898],"iteration":527,"passed_time":0.5048212865,"remaining_time":0.4512796349},
{"learn":[3.879250273],"iteration":528,"passed_time":0.5055055439,"remaining_time":0.4500814956},
{"learn":[3.877174493],"iteration":529,"passed_time":0.5060926931,"remaining_time":0.4487991806},
{"learn":[3.875854201],"iteration":530,"passed_time":0.5077162639,"remaining_time":0.4484348922},
{"learn":[3.873189396],"iteration":531,"passed_time":0.5085883335,"remaining_time":0.4474047746},
{"learn":[3.871583368],"iteration":532,"passed_time":0.5095901579,"remaining_time":0.4464889376},
{"learn":[3.869622679],"iteration":533,"passed_time":0.5107445763,"remaining_time":0.4457059411},
{"learn":[3.866860164],"iteration":534,"passed_time":0.5116909675,"remaining_time":0.4447407474},
{"learn":[3.864498444],"iteration":535,"passed_time":0.5123700372,"remaining_time":0.4435442113},
{"learn":[3.861416322],"iteration":536,"passed_time":0.5131664835,"remaining_time":0.4424508042},
{"learn":[3.860265769],"iteration":537,"passed_time":0.5138145109,"remaining_time":0.4412310484},
{"learn":[3.859328725],"iteration":538,"passed_time":0.5146838661,"remaining_time":0.4402027129},
{"learn":[3.858521278],"iteration":539,"passed_time":0.5159575916,"remaining_time":0.4395194299},
{"learn":[3.85599111],"iteration":540,"passed_time":0.5166864543,"remaining_time":0.4383716868},
{"learn":[3.852379816],"iteration":541,"passed_time":0.5174708812,"remaining_time":0.4372724421},
{"learn":[3.851327537],"iteration":542,"passed_time":0.5181262683,"remaining_time":0.4360657544},
{"learn":[3.847854898],"iteration":543,"passed_time":0.5187573189,"remaining_time":0.4348406938},
{"learn":[3.847083414],"iteration":544,"passed_time":0.5193647567,"remaining_time":0.4335980996},
{"learn":[3.845397429],"iteration":545,"passed_time":0.5199475925,"remaining_time":0.4323373755},
{"learn":[3.841933528],"iteration":546,"passed_time":0.5207121115,"remaining_time":0.4312295914},
{"learn":[3.840996474],"iteration":547,"passed_time":0.5213891091,"remaining_time":0.430050871},
{"learn":[3.838355966],"iteration":548,"passed_time":0.5221734914,"remaining_time":0.4289621942},
{"learn":[3.83342799],"iteration":549,"passed_time":0.5228674663,"remaining_time":0.4278006542},
{"learn":[3.828161535],"iteration":550,"passed_time":0.5235087516,"remaining_time":0.4265978756},
{"learn":[3.823502399],"iteration":551,"passed_time":0.5242202821,"remaining_time":0.425454142},
{"learn":[3.820068862],"iteration":552,"passed_time":0.5255027165,"remaining_time":0.4247734435},
{"learn":[3.817951642],"iteration":553,"passed_time":0.526431123,"remaining_time":0.4238055611},
{"learn":[3.815785958],"iteration":554,"passed_time":0.5270943888,"remaining_time":0.4226252307},
{"learn":[3.81503012],"iteration":555,"passed_time":0.5276526317,"remaining_time":0.4213628929},
{"learn":[3.813529315],"iteration":556,"passed_time":0.5282643651,"remaining_time":0.4201456261},
{"learn":[3.808881326],"iteration":557,"passed_time":0.5288912295,"remaining_time":0.4189425151},
{"learn":[3.808740434],"iteration":558,"passed_time":0.5308440243,"remaining_time":0.4187875039},
{"learn":[3.80714352],"iteration":559,"passed_time":0.531612838,"remaining_time":0.4176958013},
{"learn":[3.80573346],"iteration":560,"passed_time":0.5323040344,"remaining_time":0.4165445118},
{"learn":[3.803370052],"iteration":561,"passed_time":0.532933887,"remaining_time":0.4153470507},
{"learn":[3.803215211],"iteration":562,"passed_time":0.5335975742,"remaining_time":0.4141778684},
{"learn":[3.801309667],"iteration":563,"passed_time":0.5342704092,"remaining_time":0.4130175504},
{"learn":[3.800003847],"iteration":564,"passed_time":0.5348898784,"remaining_time":0.411817871},
{"learn":[3.798026138],"iteration":565,"passed_time":0.5356682365,"remaining_time":0.4107420754},
{"learn":[3.794745847],"iteration":566,"passed_time":0.5362527353,"remaining_time":0.4095192846},
{"learn":[3.794312041],"iteration":567,"passed_time":0.5369853086,"remaining_time":0.4084113615},
{"learn":[3.792205926],"iteration":568,"passed_time":0.5377536203,"remaining_time":0.4073318284},
{"learn":[3.788991061],"iteration":569,"passed_time":0.5384476963,"remaining_time":0.4061973849},
{"learn":[3.787391572],"iteration":570,"passed_time":0.5390691678,"remaining_time":0.4050099352},
{"learn":[3.7826445],"iteration":571,"passed_time":0.5399492597,"remaining_time":0.4040179775},
{"learn":[3.781700331],"iteration":572,"passed_time":0.5407601311,"remaining_time":0.4029748272},
{"learn":[3.780045374],"iteration":573,"passed_time":0.541465504,"remaining_time":0.4018541894},
{"learn":[3.775462644],"iteration":574,"passed_time":0.5421165187,"remaining_time":0.4006948182},
{"learn":[3.773711943],"iteration":575,"passed_time":0.5428777193,"remaining_time":0.3996183211},
{"learn":[3.772415806],"iteration":576,"passed_time":0.5434783621,"remaining_time":0.3984252117},
{"learn":[3.770170875],"iteration":577,"passed_time":0.5443084504,"remaining_time":0.3974016714},
{"learn":[3.765166479],"iteration":578,"passed_time":0.5450017102,"remaining_time":0.3962793092},
{"learn":[3.763976102],"iteration":579,"passed_time":0.5457017864,"remaining_time":0.3951633626},
{"learn":[3.760761708],"iteration":580,"passed_time":0.5462987344,"remaining_time":0.3939744745},
{"learn":[3.758155662],"iteration":581,"passed_time":0.5469402827,"remaining_time":0.3928196532},
{"learn":[3.756844548],"iteration":582,"passed_time":0.5475368421,"remaining_time":0.3916344137},
{"learn":[3.753098923],"iteration":583,"passed_time":0.5482536338,"remaining_time":0.3905368351},
{"learn":[3.751618946],"iteration":584,"passed_time":0.5489188507,"remaining_time":0.389403971},
{"learn":[3.751398464],"iteration":585,"passed_time":0.5495442168,"remaining_time":0.3882445491},
{"learn":[3.749920103],"iteration":586,"passed_time":0.5501413943,"remaining_time":0.3870671139},
{"learn":[3.748237465],"iteration":587,"passed_time":0.5509326764,"remaining_time":0.3860276576},
{"learn":[3.746021536],"iteration":588,"passed_time":0.5518942844,"remaining_time":0.3851078963},
{"learn":[3.74417648],"iteration":589,"passed_time":0.5525260398,"remaining_time":0.3839587734},
{"learn":[3.738788389],"iteration":590,"passed_time":0.5532077475,"remaining_time":0.3828459708},
{"learn":[3.736021611],"iteration":591,"passed_time":0.5542405386,"remaining_time":0.3819765874},
{"learn":[3.734546151],"iteration":592,"passed_time":0.5550691172,"remaining_time":0.3809664936},
{"learn":[3.733527479],"iteration":593,"passed_time":0.5558047261,"remaining_time":0.379893466},
{"learn":[3.733026392],"iteration":594,"passed_time":0.5563689718,"remaining_time":0.3787049304},
{"learn":[3.730314752],"iteration":595,"passed_time":0.5569631458,"remaining_time":0.3775387767},
{"learn":[3.727342596],"iteration":596,"passed_time":0.5575459061,"remaining_time":0.3763668344},
{"learn":[3.725459604],"iteration":597,"passed_time":0.5581130259,"remaining_time":0.3751863485},
{"learn":[3.723158842],"iteration":598,"passed_time":0.558685153,"remaining_time":0.3740112627},
{"learn":[3.722362756],"iteration":599,"passed_time":0.5612142942,"remaining_time":0.3741428628},
{"learn":[3.721443615],"iteration":600,"passed_time":0.5621650144,"remaining_time":0.373217705},
{"learn":[3.720743486],"iteration":601,"passed_time":0.5628784687,"remaining_time":0.3721355989},
{"learn":[3.720215334],"iteration":602,"passed_time":0.563533748,"remaining_time":0.3710164145},
{"learn":[3.719436563],"iteration":603,"passed_time":0.5641314502,"remaining_time":0.369861017},
{"learn":[3.715046574],"iteration":604,"passed_time":0.5648213718,"remaining_time":0.3687676725},
{"learn":[3.71443396],"iteration":605,"passed_time":0.5654201627,"remaining_time":0.3676164094},
{"learn":[3.712938941],"iteration":606,"passed_time":0.5662944488,"remaining_time":0.366645335},
{"learn":[3.712814764],"iteration":607,"passed_time":0.5669812687,"remaining_time":0.3655537127},
{"learn":[3.71235348],"iteration":608,"passed_time":0.5676146209,"remaining_time":0.3644290916},
{"learn":[3.711223749],"iteration":609,"passed_time":0.5682667329,"remaining_time":0.3633180752},
{"learn":[3.710755648],"iteration":610,"passed_time":0.5691918616,"remaining_time":0.3623823799},
{"learn":[3.708668039],"iteration":611,"passed_time":0.5701335537,"remaining_time":0.3614572204},
{"learn":[3.705623591],"iteration":612,"passed_time":0.5708791865,"remaining_time":0.3604082303},
{"learn":[3.704045802],"iteration":613,"passed_time":0.5714559606,"remaining_time":0.3592540729},
{"learn":[3.699915209],"iteration":614,"passed_time":0.5720084328,"remaining_time":0.3580865799},
{"learn":[3.696182221],"iteration":615,"passed_time":0.5725657002,"remaining_time":0.3569240728},
{"learn":[3.694263278],"iteration":616,"passed_time":0.5731849349,"remaining_time":0.3558019936},
{"learn":[3.693810229],"iteration":617,"passed_time":0.5738117823,"remaining_time":0.3546862473},
{"learn":[3.690900932],"iteration":618,"passed_time":0.5753193153,"remaining_time":0.3541141505},
{"learn":[3.688020895],"iteration":619,"passed_time":0.5759790075,"remaining_time":0.3530193917},
{"learn":[3.685491894],"iteration":620,"passed_time":0.576919654,"remaining_time":0.3520975022},
{"learn":[3.684328128],"iteration":621,"passed_time":0.5775496279,"remaining_time":0.3509867514},
{"learn":[3.680640153],"iteration":622,"passed_time":0.5786720285,"remaining_time":0.3501755293},
{"learn":[3.678932783],"iteration":623,"passed_time":0.579468678,"remaining_time":0.3491670239},
{"learn":[3.674167041],"iteration":624,"passed_time":0.5801321072,"remaining_time":0.3480792643},
{"learn":[3.672200976],"iteration":625,"passed_time":0.5810249323,"remaining_time":0.3471299116},
{"learn":[3.670606604],"iteration":626,"passed_time":0.5816878467,"remaining_time":0.3460439662},
{"learn":[3.665506042],"iteration":627,"passed_time":0.5824480185,"remaining_time":0.3450169791},
{"learn":[3.664214007],"iteration":628,"passed_time":0.5832595545,"remaining_time":0.3440211363},
{"learn":[3.66261643],"iteration":629,"passed_time":0.5838875047,"remaining_time":0.3429180583},
{"learn":[3.662118449],"iteration":630,"passed_time":0.5846395497,"remaining_time":0.3418890552},
{"learn":[3.660871366],"iteration":631,"passed_time":0.5857591384,"remaining_time":0.3410749414},
{"learn":[3.656695243],"iteration":632,"passed_time":0.5865484323,"remaining_time":0.3400683644},
{"learn":[3.654497801],"iteration":633,"passed_time":0.5872217986,"remaining_time":0.3389955493},
{"learn":[3.654189134],"iteration":634,"passed_time":0.5878230512,"remaining_time":0.3378825412},
{"learn":[3.653957699],"iteration":635,"passed_time":0.5884420931,"remaining_time":0.3367813237},
{"learn":[3.651920725],"iteration":636,"passed_time":0.5893366794,"remaining_time":0.3358386415},
{"learn":[3.65106705],"iteration":637,"passed_time":0.5900005958,"remaining_time":0.3347652283},
{"learn":[3.650612844],"iteration":638,"passed_time":0.5907845904,"remaining_time":0.3337609345},
{"learn":[3.649884732],"iteration":639,"passed_time":0.5914475474,"remaining_time":0.3326892454},
{"learn":[3.646276182],"iteration":640,"passed_time":0.5922238921,"remaining_time":0.3316823358},
{"learn":[3.645808194],"iteration":641,"passed_time":0.5929845015,"remaining_time":0.33066737},
{"learn":[3.645042989],"iteration":642,"passed_time":0.5936536688,"remaining_time":0.3296024257},
{"learn":[3.639864499],"iteration":643,"passed_time":0.5942892032,"remaining_time":0.3285201185},
{"learn":[3.637318478],"iteration":644,"passed_time":0.594964739,"remaining_time":0.3274612129},
{"learn":[3.636344905],"iteration":645,"passed_time":0.5957378033,"remaining_time":0.3264569386},
{"learn":[3.634754643],"iteration":646,"passed_time":0.5965830201,"remaining_time":0.3254927451},
{"learn":[3.630724975],"iteration":647,"passed_time":0.5973663856,"remaining_time":0.3244953206},
{"learn":[3.629408252],"iteration":648,"passed_time":0.5983099017,"remaining_time":0.3235851703},
{"learn":[3.62790646],"iteration":649,"passed_time":0.5989059104,"remaining_time":0.3224877979},
{"learn":[3.627388973],"iteration":650,"passed_time":0.5998232562,"remaining_time":0.3215642341},
{"learn":[3.625163557],"iteration":651,"passed_time":0.6006489106,"remaining_time":0.3205917498},
{"learn":[3.623701985],"iteration":652,"passed_time":0.6012819143,"remaining_time":0.3195173419},
{"learn":[3.622342639],"iteration":653,"passed_time":0.6018848752,"remaining_time":0.3184283897},
{"learn":[3.621130639],"iteration":654,"passed_time":0.6024113674,"remaining_time":0.3173006439},
{"learn":[3.619125665],"iteration":655,"passed_time":0.6029497387,"remaining_time":0.3161809605},
{"learn":[3.618878783],"iteration":656,"passed_time":0.6034877772,"remaining_time":0.315062873},
{"learn":[3.616207429],"iteration":657,"passed_time":0.6043156073,"remaining_time":0.3140971697},
{"learn":[3.61206486],"iteration":658,"passed_time":0.6052604015,"remaining_time":0.3131924081},
{"learn":[3.611955873],"iteration":659,"passed_time":0.606292791,"remaining_time":0.3123326499},
{"learn":[3.610713743],"iteration":660,"passed_time":0.6069328667,"remaining_time":0.3112711676},
{"learn":[3.610044025],"iteration":661,"passed_time":0.6075839417,"remaining_time":0.3102165745},
{"learn":[3.607342669],"iteration":662,"passed_time":0.608187353,"remaining_time":0.3091389713},
{"learn":[3.602510618],"iteration":663,"passed_time":0.6087830798,"remaining_time":0.3080589078},
{"learn":[3.600492392],"iteration":664,"passed_time":0.6093323938,"remaining_time":0.3069569202},
{"learn":[3.597171065],"iteration":665,"passed_time":0.609862872,"remaining_time":0.305847146},
{"learn":[3.594358798],"iteration":666,"passed_time":0.6104985356,"remaining_time":0.3047916227},
{"learn":[3.593945251],"iteration":667,"passed_time":0.6111517797,"remaining_time":0.3037460941},
{"learn":[3.593607748],"iteration":668,"passed_time":0.6118315207,"remaining_time":0.302714848},
{"learn":[3.592238714],"iteration":669,"passed_time":0.6127401249,"remaining_time":0.301797375},
{"learn":[3.590144654],"iteration":670,"passed_time":0.6136002358,"remaining_time":0.3008561514},
{"learn":[3.587151536],"iteration":671,"passed_time":0.6143753841,"remaining_time":0.2998736994},
{"learn":[3.586070865],"iteration":672,"passed_time":0.6152691142,"remaining_time":0.2989494804},
{"learn":[3.585102746],"iteration":673,"passed_time":0.6159922323,"remaining_time":0.2979428304},
{"learn":[3.584362847],"iteration":674,"passed_time":0.616743568,"remaining_time":0.2969506068},
{"learn":[3.581407561],"iteration":675,"passed_time":0.6174232503,"remaining_time":0.2959247531},
{"learn":[3.57919422],"iteration":676,"passed_time":0.6182553074,"remaining_time":0.2949726208},
{"learn":[3.577632204],"iteration":677,"passed_time":0.6190275758,"remaining_time":0.2939924475},
{"learn":[3.573911195],"iteration":678,"passed_time":0.619630436,"remaining_time":0.2929327982},
{"learn":[3.573408216],"iteration":679,"passed_time":0.6203122383,"remaining_time":0.2919116415},
{"learn":[3.571076482],"iteration":680,"passed_time":0.6209117644,"remaining_time":0.290852941},
{"learn":[3.568177107],"iteration":681,"passed_time":0.6215625991,"remaining_time":0.289819511},
{"learn":[3.564824621],"iteration":682,"passed_time":0.6224335164,"remaining_time":0.288889348},
{"learn":[3.562475026],"iteration":683,"passed_time":0.6230583323,"remaining_time":0.2878456623},
{"learn":[3.561226889],"iteration":684,"passed_time":0.6237817274,"remaining_time":0.2868485316},
{"learn":[3.559383467],"iteration":685,"passed_time":0.6246947416,"remaining_time":0.2859389925},
{"learn":[3.555209766],"iteration":686,"passed_time":0.6254815779,"remaining_time":0.2849719562},
{"learn":[3.55345383],"iteration":687,"passed_time":0.6262027837,"remaining_time":0.283975681},
{"learn":[3.552300968],"iteration":688,"passed_time":0.6268361433,"remaining_time":0.2829405523},
{"learn":[3.551253986],"iteration":689,"passed_time":0.627753312,"remaining_time":0.2820340967},
{"learn":[3.549807725],"iteration":690,"passed_time":0.6285000482,"remaining_time":0.2810513964},
{"learn":[3.547992926],"iteration":691,"passed_time":0.6292221796,"remaining_time":0.2800584268},
{"learn":[3.545438607],"iteration":692,"passed_time":0.6298641288,"remaining_time":0.2790307179},
{"learn":[3.543313763],"iteration":693,"passed_time":0.6304225488,"remaining_time":0.277967291},
{"learn":[3.542962896],"iteration":694,"passed_time":0.6309779997,"remaining_time":0.2769040142},
{"learn":[3.539800465],"iteration":695,"passed_time":0.6314917838,"remaining_time":0.2758239975},
{"learn":[3.53953187],"iteration":696,"passed_time":0.6320315092,"remaining_time":0.2747568828},
{"learn":[3.536332425],"iteration":697,"passed_time":0.6325823809,"remaining_time":0.2736961018},
{"learn":[3.534993327],"iteration":698,"passed_time":0.6334912948,"remaining_time":0.2727909581},
{"learn":[3.531637011],"iteration":699,"passed_time":0.6342307411,"remaining_time":0.2718131748},
{"learn":[3.531040284],"iteration":700,"passed_time":0.6348962721,"remaining_time":0.270804544},
{"learn":[3.529973872],"iteration":701,"passed_time":0.6355983981,"remaining_time":0.2698124254},
{"learn":[3.527325183],"iteration":702,"passed_time":0.6363144475,"remaining_time":0.2688270141},
{"learn":[3.527200815],"iteration":703,"passed_time":0.6370449162,"remaining_time":0.2678484307},
{"learn":[3.523459911],"iteration":704,"passed_time":0.6377548589,"remaining_time":0.2668619622},
{"learn":[3.522729934],"iteration":705,"passed_time":0.6383876277,"remaining_time":0.2658441396},
{"learn":[3.522260582],"iteration":706,"passed_time":0.6389940186,"remaining_time":0.2648164745},
{"learn":[3.518641591],"iteration":707,"passed_time":0.6395861606,"remaining_time":0.2637841227},
{"learn":[3.516856405],"iteration":708,"passed_time":0.6403719772,"remaining_time":0.262832504},
{"learn":[3.515083413],"iteration":709,"passed_time":0.6413358773,"remaining_time":0.2619540907},
{"learn":[3.514671214],"iteration":710,"passed_time":0.6420866127,"remaining_time":0.2609887919},
{"learn":[3.512617621],"iteration":711,"passed_time":0.6432129914,"remaining_time":0.2601760415},
{"learn":[3.510747971],"iteration":712,"passed_time":0.6440707458,"remaining_time":0.2592542834},
{"learn":[3.508149266],"iteration":713,"passed_time":0.644961254,"remaining_time":0.2583458244},
{"learn":[3.504557165],"iteration":714,"passed_time":0.645693474,"remaining_time":0.2573743218},
{"learn":[3.501367208],"iteration":715,"passed_time":0.646466047,"remaining_time":0.2564194935},
{"learn":[3.497593362],"iteration":716,"passed_time":0.647185206,"remaining_time":0.2554440911},
{"learn":[3.496291169],"iteration":717,"passed_time":0.6483413476,"remaining_time":0.2546410307},
{"learn":[3.49330374],"iteration":718,"passed_time":0.6492297652,"remaining_time":0.2537323561},
{"learn":[3.490044385],"iteration":719,"passed_time":0.6501687574,"remaining_time":0.2528434057},
{"learn":[3.488891789],"iteration":720,"passed_time":0.6513434302,"remaining_time":0.252045516},
{"learn":[3.486869081],"iteration":721,"passed_time":0.6521615973,"remaining_time":0.2511093131},
{"learn":[3.486303638],"iteration":722,"passed_time":0.6528193153,"remaining_time":0.2501119645},
{"learn":[3.486035862],"iteration":723,"passed_time":0.6535190662,"remaining_time":0.2491315777},
{"learn":[3.482668951],"iteration":724,"passed_time":0.6542422355,"remaining_time":0.2481608479},
{"learn":[3.47820549],"iteration":725,"passed_time":0.6548586278,"remaining_time":0.2471505014},
{"learn":[3.474392283],"iteration":726,"passed_time":0.6554723457,"remaining_time":0.2461402344},
{"learn":[3.472268163],"iteration":727,"passed_time":0.6563252372,"remaining_time":0.2452204183},
{"learn":[3.471209164],"iteration":728,"passed_time":0.6570687,"remaining_time":0.2442601066},
{"learn":[3.470049971],"iteration":729,"passed_time":0.6576923831,"remaining_time":0.2432560869},
{"learn":[3.469078654],"iteration":730,"passed_time":0.6583117763,"remaining_time":0.2422515292},
{"learn":[3.468643292],"iteration":731,"passed_time":0.6589804313,"remaining_time":0.2412660595},
{"learn":[3.468134848],"iteration":732,"passed_time":0.6596680344,"remaining_time":0.2402883563},
{"learn":[3.467820182],"iteration":733,"passed_time":0.660703367,"remaining_time":0.23943746},
{"learn":[3.465776156],"iteration":734,"passed_time":0.6614435048,"remaining_time":0.238479631},
{"learn":[3.463037608],"iteration":735,"passed_time":0.6621852973,"remaining_time":0.2375229871},
{"learn":[3.45965637],"iteration":736,"passed_time":0.6629456692,"remaining_time":0.2365735563},
{"learn":[3.457275091],"iteration":737,"passed_time":0.6636038496,"remaining_time":0.2355883585},
{"learn":[3.455522955],"iteration":738,"passed_time":0.6645070676,"remaining_time":0.2346905881},
{"learn":[3.451270508],"iteration":739,"passed_time":0.6658325513,"remaining_time":0.2339411667},
{"learn":[3.450978947],"iteration":740,"passed_time":0.666729762,"remaining_time":0.2330404971},
{"learn":[3.450608492],"iteration":741,"passed_time":0.667577633,"remaining_time":0.232122681},
{"learn":[3.448122004],"iteration":742,"passed_time":0.6683136973,"remaining_time":0.2311663798},
{"learn":[3.445646714],"iteration":743,"passed_time":0.6689387237,"remaining_time":0.2301724641},
{"learn":[3.44411263],"iteration":744,"passed_time":0.6701247207,"remaining_time":0.2293715487},
{"learn":[3.443264164],"iteration":745,"passed_time":0.6708831742,"remaining_time":0.2284240298},
{"learn":[3.439521363],"iteration":746,"passed_time":0.6717138458,"remaining_time":0.2275014766},
{"learn":[3.436809225],"iteration":747,"passed_time":0.6723683238,"remaining_time":0.2265198096},
{"learn":[3.435509465],"iteration":748,"passed_time":0.6729693448,"remaining_time":0.2255211022},
{"learn":[3.434450277],"iteration":749,"passed_time":0.6742904595,"remaining_time":0.2247634865},
{"learn":[3.431786753],"iteration":750,"passed_time":0.6749879955,"remaining_time":0.2237976177},
{"learn":[3.430150302],"iteration":751,"passed_time":0.6756744517,"remaining_time":0.2228288085},
{"learn":[3.42696281],"iteration":752,"passed_time":0.6763569818,"remaining_time":0.2218594615},
{"learn":[3.426870334],"iteration":753,"passed_time":0.6770027266,"remaining_time":0.2208788737},
{"learn":[3.425200309],"iteration":754,"passed_time":0.6775917249,"remaining_time":0.2198807584},
{"learn":[3.423383783],"iteration":755,"passed_time":0.6784752962,"remaining_time":0.2189787993},
{"learn":[3.422752979],"iteration":756,"passed_time":0.6790804469,"remaining_time":0.2179875146},
{"learn":[3.420845924],"iteration":757,"passed_time":0.6798125933,"remaining_time":0.2170377937},
{"learn":[3.418917862],"iteration":758,"passed_time":0.6804377523,"remaining_time":0.216054675},
{"learn":[3.417095735],"iteration":759,"passed_time":0.6810891064,"remaining_time":0.2150807704},
{"learn":[3.414391848],"iteration":760,"passed_time":0.6817809741,"remaining_time":0.2141204373},
{"learn":[3.41426711],"iteration":761,"passed_time":0.6824089143,"remaining_time":0.213140842},
{"learn":[3.411976013],"iteration":762,"passed_time":0.6829922839,"remaining_time":0.2121483241},
{"learn":[3.408614844],"iteration":763,"passed_time":0.6835845672,"remaining_time":0.2111596307},
{"learn":[3.407906721],"iteration":764,"passed_time":0.6843262907,"remaining_time":0.2102178802},
{"learn":[3.407494015],"iteration":765,"passed_time":0.6850275605,"remaining_time":0.2092642939},
{"learn":[3.406287128],"iteration":766,"passed_time":0.6857788677,"remaining_time":0.2083265661},
{"learn":[3.404600442],"iteration":767,"passed_time":0.686679259,"remaining_time":0.2074343595},
{"learn":[3.404012662],"iteration":768,"passed_time":0.6875950384,"remaining_time":0.2065467541},
{"learn":[3.400398762],"iteration":769,"passed_time":0.6882603444,"remaining_time":0.2055842587},
{"learn":[3.399737714],"iteration":770,"passed_time":0.6888141126,"remaining_time":0.2045894057},
{"learn":[3.399185251],"iteration":771,"passed_time":0.6893793362,"remaining_time":0.2035990786},
{"learn":[3.397245411],"iteration":772,"passed_time":0.6899420654,"remaining_time":0.2026091188},
{"learn":[3.396229831],"iteration":773,"passed_time":0.6904935824,"remaining_time":0.2016169892},
{"learn":[3.394002836],"iteration":774,"passed_time":0.6910685701,"remaining_time":0.2006328107},
{"learn":[3.389617243],"iteration":775,"passed_time":0.691633115,"remaining_time":0.1996466724},
{"learn":[3.385426488],"iteration":776,"passed_time":0.6921990888,"remaining_time":0.1986620293},
{"learn":[3.385072258],"iteration":777,"passed_time":0.6929234995,"remaining_time":0.1977236721},
{"learn":[3.383842366],"iteration":778,"passed_time":0.6936703938,"remaining_time":0.1967922427},
{"learn":[3.380110746],"iteration":779,"passed_time":0.6944682628,"remaining_time":0.1958756639},
{"learn":[3.378595218],"iteration":780,"passed_time":0.695201659,"remaining_time":0.1949413103},
{"learn":[3.377371219],"iteration":781,"passed_time":0.6961762417,"remaining_time":0.1940747068},
{"learn":[3.375814782],"iteration":782,"passed_time":0.6973784258,"remaining_time":0.1932709047},
{"learn":[3.374195887],"iteration":783,"passed_time":0.6980339458,"remaining_time":0.1923154749},
{"learn":[3.373704309],"iteration":784,"passed_time":0.6986895554,"remaining_time":0.1913608336},
{"learn":[3.372971757],"iteration":785,"passed_time":0.6994046582,"remaining_time":0.1904231512},
{"learn":[3.371565136],"iteration":786,"passed_time":0.6999567444,"remaining_time":0.1894419143},
{"learn":[3.3700309],"iteration":787,"passed_time":0.7005271381,"remaining_time":0.188466692},
{"learn":[3.368186663],"iteration":788,"passed_time":0.7011732623,"remaining_time":0.1875127482},
{"learn":[3.366710398],"iteration":789,"passed_time":0.7017380409,"remaining_time":0.1865379602},
{"learn":[3.364598042],"iteration":790,"passed_time":0.7022861085,"remaining_time":0.1855597935},
{"learn":[3.36348442],"iteration":791,"passed_time":0.7028609711,"remaining_time":0.18458975},
{"learn":[3.362001759],"iteration":792,"passed_time":0.7035575936,"remaining_time":0.1836524866},
{"learn":[3.361580401],"iteration":793,"passed_time":0.7041333037,"remaining_time":0.1826844592},
{"learn":[3.359543675],"iteration":794,"passed_time":0.704702958,"remaining_time":0.1817158571},
{"learn":[3.35766119],"iteration":795,"passed_time":0.7052487806,"remaining_time":0.1807421498},
{"learn":[3.354592969],"iteration":796,"passed_time":0.7058281002,"remaining_time":0.1797780481},
{"learn":[3.350985986],"iteration":797,"passed_time":0.7063959442,"remaining_time":0.1788120059},
{"learn":[3.349589624],"iteration":798,"passed_time":0.7069613123,"remaining_time":0.1778463376},
{"learn":[3.349110856],"iteration":799,"passed_time":0.7075287777,"remaining_time":0.1768821944},
{"learn":[3.345315441],"iteration":800,"passed_time":0.7084095978,"remaining_time":0.1759968913},
{"learn":[3.34397474],"iteration":801,"passed_time":0.7091435335,"remaining_time":0.1750753362},
{"learn":[3.343800902],"iteration":802,"passed_time":0.7101565521,"remaining_time":0.1742227158},
{"learn":[3.342329465],"iteration":803,"passed_time":0.7108507495,"remaining_time":0.1732919738},
{"learn":[3.34220347],"iteration":804,"passed_time":0.7114789676,"remaining_time":0.1723458369},
{"learn":[3.341279219],"iteration":805,"passed_time":0.7120594358,"remaining_time":0.1713889957},
{"learn":[3.337329521],"iteration":806,"passed_time":0.7126466469,"remaining_time":0.1704346999},
{"learn":[3.336708453],"iteration":807,"passed_time":0.7131910972,"remaining_time":0.1694711518},
{"learn":[3.333252703],"iteration":808,"passed_time":0.713823802,"remaining_time":0.1685294761},
{"learn":[3.332186769],"iteration":809,"passed_time":0.7144562001,"remaining_time":0.1675884914},
{"learn":[3.330594851],"iteration":810,"passed_time":0.7151352698,"remaining_time":0.1666591443},
{"learn":[3.327867442],"iteration":811,"passed_time":0.7157413717,"remaining_time":0.1657135195},
{"learn":[3.327563111],"iteration":812,"passed_time":0.7167277369,"remaining_time":0.1648561953},
{"learn":[3.326308994],"iteration":813,"passed_time":0.7174404621,"remaining_time":0.163936027},
{"learn":[3.326249879],"iteration":814,"passed_time":0.7180823861,"remaining_time":0.1630002962},
{"learn":[3.322336238],"iteration":815,"passed_time":0.7186681601,"remaining_time":0.1620526243},
{"learn":[3.320491154],"iteration":816,"passed_time":0.7192082372,"remaining_time":0.1610956027},
{"learn":[3.320434271],"iteration":817,"passed_time":0.7197268578,"remaining_time":0.1601348265},
{"learn":[3.319609638],"iteration":818,"passed_time":0.720248066,"remaining_time":0.159175702},
{"learn":[3.316182682],"iteration":819,"passed_time":0.7207878422,"remaining_time":0.1582217215},
{"learn":[3.313126612],"iteration":820,"passed_time":0.7213084535,"remaining_time":0.1572645715},
{"learn":[3.311222803],"iteration":821,"passed_time":0.721848221,"remaining_time":0.1563126318},
{"learn":[3.309627335],"iteration":822,"passed_time":0.7223930194,"remaining_time":0.1553627757},
{"learn":[3.307974895],"iteration":823,"passed_time":0.7232226634,"remaining_time":0.1544747436},
{"learn":[3.307321505],"iteration":824,"passed_time":0.7240724512,"remaining_time":0.153591126},
{"learn":[3.306759087],"iteration":825,"passed_time":0.7247503732,"remaining_time":0.1526713861},
{"learn":[3.30484037],"iteration":826,"passed_time":0.7254498908,"remaining_time":0.1517567486},
{"learn":[3.30201994],"iteration":827,"passed_time":0.7260598837,"remaining_time":0.1508240338},
{"learn":[3.299302297],"iteration":828,"passed_time":0.7267283525,"remaining_time":0.1499041596},
{"learn":[3.298132671],"iteration":829,"passed_time":0.7273538025,"remaining_time":0.14897608},
{"learn":[3.296976183],"iteration":830,"passed_time":0.7279583648,"remaining_time":0.1480444809},
{"learn":[3.293144745],"iteration":831,"passed_time":0.7286700765,"remaining_time":0.1471353039},
{"learn":[3.290284404],"iteration":832,"passed_time":0.7294156378,"remaining_time":0.1462333872},
{"learn":[3.288285745],"iteration":833,"passed_time":0.7301641109,"remaining_time":0.145332425},
{"learn":[3.286662667],"iteration":834,"passed_time":0.73087889,"remaining_time":0.1444251699},
{"learn":[3.285692682],"iteration":835,"passed_time":0.7319339415,"remaining_time":0.1435851273},
{"learn":[3.284565611],"iteration":836,"passed_time":0.7327387933,"remaining_time":0.1426958462},
{"learn":[3.283897383],"iteration":837,"passed_time":0.7333465415,"remaining_time":0.1417686632},
{"learn":[3.280712855],"iteration":838,"passed_time":0.7339213038,"remaining_time":0.1408359117},
{"learn":[3.280468341],"iteration":839,"passed_time":0.7344915881,"remaining_time":0.1399031596},
{"learn":[3.277814895],"iteration":840,"passed_time":0.7350722784,"remaining_time":0.1389732369},
{"learn":[3.276316385],"iteration":841,"passed_time":0.7356266695,"remaining_time":0.1380392088},
{"learn":[3.27557063],"iteration":842,"passed_time":0.736238338,"remaining_time":0.1371167486},
{"learn":[3.27499628],"iteration":843,"passed_time":0.7367944247,"remaining_time":0.1361847515},
{"learn":[3.273569958],"iteration":844,"passed_time":0.7373779277,"remaining_time":0.1352586731},
{"learn":[3.269665595],"iteration":845,"passed_time":0.738215561,"remaining_time":0.1343796648},
{"learn":[3.267984685],"iteration":846,"passed_time":0.7390013408,"remaining_time":0.1334913874},
{"learn":[3.267702508],"iteration":847,"passed_time":0.7397921494,"remaining_time":0.1326042532},
{"learn":[3.266671924],"iteration":848,"passed_time":0.7406050519,"remaining_time":0.1317212754},
{"learn":[3.265359825],"iteration":849,"passed_time":0.7412176329,"remaining_time":0.1308031117},
{"learn":[3.2618983],"iteration":850,"passed_time":0.7417809954,"remaining_time":0.1298770486},
{"learn":[3.260456253],"iteration":851,"passed_time":0.74258712,"remaining_time":0.1289940068},
{"learn":[3.258389147],"iteration":852,"passed_time":0.7432902929,"remaining_time":0.1280934034},
{"learn":[3.258108469],"iteration":853,"passed_time":0.7439086714,"remaining_time":0.1271787658},
{"learn":[3.256424936],"iteration":854,"passed_time":0.7447574671,"remaining_time":0.1263038979},
{"learn":[3.254817983],"iteration":855,"passed_time":0.7457782335,"remaining_time":0.1254580206},
{"learn":[3.253898449],"iteration":856,"passed_time":0.7465912269,"remaining_time":0.1245770659},
{"learn":[3.253023652],"iteration":857,"passed_time":0.7475366598,"remaining_time":0.1237181885},
{"learn":[3.252845542],"iteration":858,"passed_time":0.7482686449,"remaining_time":0.1228240733},
{"learn":[3.252316026],"iteration":859,"passed_time":0.7488651184,"remaining_time":0.1219082751},
{"learn":[3.24975301],"iteration":860,"passed_time":0.7494539933,"remaining_time":0.1209919919},
{"learn":[3.249151075],"iteration":861,"passed_time":0.7500237507,"remaining_time":0.1200734079},
{"learn":[3.246257135],"iteration":862,"passed_time":0.7506124253,"remaining_time":0.1191586353},
{"learn":[3.243826471],"iteration":863,"passed_time":0.7511597833,"remaining_time":0.118238114},
{"learn":[3.243190653],"iteration":864,"passed_time":0.7517237998,"remaining_time":0.1173210555},
{"learn":[3.24008797],"iteration":865,"passed_time":0.7522720317,"remaining_time":0.1164023698},
{"learn":[3.240036811],"iteration":866,"passed_time":0.753836379,"remaining_time":0.1156404134},
{"learn":[3.238676314],"iteration":867,"passed_time":0.7545870463,"remaining_time":0.1147528688},
{"learn":[3.237848782],"iteration":868,"passed_time":0.755224709,"remaining_time":0.113848604},
{"learn":[3.236405498],"iteration":869,"passed_time":0.7565089677,"remaining_time":0.1130415699},
{"learn":[3.233378068],"iteration":870,"passed_time":0.7575998781,"remaining_time":0.112204804},
{"learn":[3.233169169],"iteration":871,"passed_time":0.7583409555,"remaining_time":0.1113161036},
{"learn":[3.232434885],"iteration":872,"passed_time":0.7589831161,"remaining_time":0.1104133514},
{"learn":[3.229978115],"iteration":873,"passed_time":0.759607299,"remaining_time":0.1095086038},
{"learn":[3.229648848],"iteration":874,"passed_time":0.76015991,"remaining_time":0.1085942729},
{"learn":[3.227208761],"iteration":875,"passed_time":0.7608717266,"remaining_time":0.1077033038},
{"learn":[3.226258869],"iteration":876,"passed_time":0.7616622569,"remaining_time":0.1068237829},
{"learn":[3.225331995],"iteration":877,"passed_time":0.7624958894,"remaining_time":0.1059504539},
{"learn":[3.221968268],"iteration":878,"passed_time":0.7637328705,"remaining_time":0.1051327387},
{"learn":[3.221166317],"iteration":879,"passed_time":0.7644808428,"remaining_time":0.1042473877},
{"learn":[3.220047503],"iteration":880,"passed_time":0.7650617428,"remaining_time":0.1033397814},
{"learn":[3.21982781],"iteration":881,"passed_time":0.7656929499,"remaining_time":0.1024396464},
{"learn":[3.216693405],"iteration":882,"passed_time":0.7662718261,"remaining_time":0.1015331865},
{"learn":[3.214798761],"iteration":883,"passed_time":0.7668749799,"remaining_time":0.1006306535},
{"learn":[3.214395085],"iteration":884,"passed_time":0.7674426562,"remaining_time":0.09972418696},
{"learn":[3.213470696],"iteration":885,"passed_time":0.7692328105,"remaining_time":0.09897577923},
{"learn":[3.211595017],"iteration":886,"passed_time":0.7700977908,"remaining_time":0.09810715937},
{"learn":[3.210965255],"iteration":887,"passed_time":0.7708145297,"remaining_time":0.09721985059},
{"learn":[3.209413583],"iteration":888,"passed_time":0.7714258705,"remaining_time":0.0963197656},
{"learn":[3.208331683],"iteration":889,"passed_time":0.7720344374,"remaining_time":0.09541998664},
{"learn":[3.207110711],"iteration":890,"passed_time":0.7726717016,"remaining_time":0.09452437203},
{"learn":[3.204519413],"iteration":891,"passed_time":0.7732061666,"remaining_time":0.09361689012},
{"learn":[3.201421296],"iteration":892,"passed_time":0.7737755772,"remaining_time":0.09271443087},
{"learn":[3.200691259],"iteration":893,"passed_time":0.7745361036,"remaining_time":0.09183537694},
{"learn":[3.200485067],"iteration":894,"passed_time":0.7754796626,"remaining_time":0.09097806098},
{"learn":[3.197467568],"iteration":895,"passed_time":0.7762355474,"remaining_time":0.0900987689},
{"learn":[3.195838544],"iteration":896,"passed_time":0.7772221059,"remaining_time":0.08924623958},
{"learn":[3.195671746],"iteration":897,"passed_time":0.7778815817,"remaining_time":0.08835625984},
{"learn":[3.194213094],"iteration":898,"passed_time":0.7785562439,"remaining_time":0.08746849904},
{"learn":[3.192884691],"iteration":899,"passed_time":0.7791235524,"remaining_time":0.0865692836},
{"learn":[3.188364239],"iteration":900,"passed_time":0.7796936983,"remaining_time":0.08567111669},
{"learn":[3.185219478],"iteration":901,"passed_time":0.7803279786,"remaining_time":0.08478064512},
{"learn":[3.184120387],"iteration":902,"passed_time":0.7809094995,"remaining_time":0.08388507359},
{"learn":[3.183725321],"iteration":903,"passed_time":0.781476668,"remaining_time":0.08298867271},
{"learn":[3.181264554],"iteration":904,"passed_time":0.7820663801,"remaining_time":0.08209536587},
{"learn":[3.180741589],"iteration":905,"passed_time":0.7826261712,"remaining_time":0.08119962482},
{"learn":[3.179782639],"iteration":906,"passed_time":0.7835320197,"remaining_time":0.08034010787},
{"learn":[3.176377564],"iteration":907,"passed_time":0.7847264849,"remaining_time":0.07950973195},
{"learn":[3.174078182],"iteration":908,"passed_time":0.7854999592,"remaining_time":0.07863640955},
{"learn":[3.171242379],"iteration":909,"passed_time":0.786210375,"remaining_time":0.07775707005},
{"learn":[3.170421012],"iteration":910,"passed_time":0.786826688,"remaining_time":0.07686890805},
{"learn":[3.170087224],"iteration":911,"passed_time":0.7874170243,"remaining_time":0.07597883568},
{"learn":[3.167303059],"iteration":912,"passed_time":0.7880217196,"remaining_time":0.07509078817},
{"learn":[3.16705966],"iteration":913,"passed_time":0.7886004972,"remaining_time":0.07420092205},
{"learn":[3.165667683],"iteration":914,"passed_time":0.7892745195,"remaining_time":0.07332058377},
{"learn":[3.164689733],"iteration":915,"passed_time":0.7898666413,"remaining_time":0.07243318544},
{"learn":[3.163311455],"iteration":916,"passed_time":0.7905863848,"remaining_time":0.07155798248},
{"learn":[3.159425016],"iteration":917,"passed_time":0.7912279855,"remaining_time":0.07067613814},
{"learn":[3.159327058],"iteration":918,"passed_time":0.792203249,"remaining_time":0.06982422543},
{"learn":[3.15819426],"iteration":919,"passed_time":0.7928294921,"remaining_time":0.06894169497},
{"learn":[3.157086603],"iteration":920,"passed_time":0.7934972277,"remaining_time":0.06806328012},
{"learn":[3.153354154],"iteration":921,"passed_time":0.7940651789,"remaining_time":0.06717688065},
{"learn":[3.153261317],"iteration":922,"passed_time":0.7945800307,"remaining_time":0.06628674146},
{"learn":[3.153168454],"iteration":923,"passed_time":0.7951012708,"remaining_time":0.06539794002},
{"learn":[3.152080399],"iteration":924,"passed_time":0.7956280255,"remaining_time":0.06451038045},
{"learn":[3.151635144],"iteration":925,"passed_time":0.7961732165,"remaining_time":0.06362507346},
{"learn":[3.147762655],"iteration":926,"passed_time":0.7967667536,"remaining_time":0.06274430745},
{"learn":[3.147172317],"iteration":927,"passed_time":0.7973387267,"remaining_time":0.06186248742},
{"learn":[3.146254125],"iteration":928,"passed_time":0.7981251084,"remaining_time":0.06099772088},
{"learn":[3.144869828],"iteration":929,"passed_time":0.7991009611,"remaining_time":0.06014738417},
{"learn":[3.143466218],"iteration":930,"passed_time":0.7997106179,"remaining_time":0.05926963763},
{"learn":[3.141919643],"iteration":931,"passed_time":0.8002992173,"remaining_time":0.05839093002},
{"learn":[3.141054135],"iteration":932,"passed_time":0.8009129105,"remaining_time":0.0575146463},
{"learn":[3.139390417],"iteration":933,"passed_time":0.8015262151,"remaining_time":0.05663889743},
{"learn":[3.139025283],"iteration":934,"passed_time":0.8021394529,"remaining_time":0.05576370528},
{"learn":[3.137824183],"iteration":935,"passed_time":0.8028424351,"remaining_time":0.05489520924},
{"learn":[3.135620453],"iteration":936,"passed_time":0.803415217,"remaining_time":0.05401831235},
{"learn":[3.13443178],"iteration":937,"passed_time":0.8040667949,"remaining_time":0.05314727215},
{"learn":[3.132765713],"iteration":938,"passed_time":0.804772778,"remaining_time":0.05228023371},
{"learn":[3.131434124],"iteration":939,"passed_time":0.8054190186,"remaining_time":0.05140972459},
{"learn":[3.128384262],"iteration":940,"passed_time":0.806526905,"remaining_time":0.05056863698},
{"learn":[3.128120455],"iteration":941,"passed_time":0.8072045512,"remaining_time":0.04970049254},
{"learn":[3.126314615],"iteration":942,"passed_time":0.8078486112,"remaining_time":0.04883072199},
{"learn":[3.125409666],"iteration":943,"passed_time":0.8084414217,"remaining_time":0.04795838942},
{"learn":[3.123072589],"iteration":944,"passed_time":0.809008847,"remaining_time":0.04708517099},
{"learn":[3.122921099],"iteration":945,"passed_time":0.8095939712,"remaining_time":0.04621360935},
{"learn":[3.122182662],"iteration":946,"passed_time":0.8101966567,"remaining_time":0.04534363549},
{"learn":[3.120040951],"iteration":947,"passed_time":0.8107700691,"remaining_time":0.04447261982},
{"learn":[3.118767799],"iteration":948,"passed_time":0.8113298919,"remaining_time":0.04360150104},
{"learn":[3.118203218],"iteration":949,"passed_time":0.8119572571,"remaining_time":0.04273459248},
{"learn":[3.116343362],"iteration":950,"passed_time":0.8126089319,"remaining_time":0.04186944024},
{"learn":[3.11480829],"iteration":951,"passed_time":0.8134715103,"remaining_time":0.04101537027},
{"learn":[3.112607903],"iteration":952,"passed_time":0.8143700417,"remaining_time":0.04016305557},
{"learn":[3.111661241],"iteration":953,"passed_time":0.8150387652,"remaining_time":0.0392995631},
{"learn":[3.110249676],"iteration":954,"passed_time":0.815653978,"remaining_time":0.03843395708},
{"learn":[3.107333579],"iteration":955,"passed_time":0.816910619,"remaining_time":0.03759839669},
{"learn":[3.107149851],"iteration":956,"passed_time":0.8177120132,"remaining_time":0.03674150112},
{"learn":[3.106867336],"iteration":957,"passed_time":0.8184049572,"remaining_time":0.03587996681},
{"learn":[3.10364681],"iteration":958,"passed_time":0.8191970386,"remaining_time":0.0350230225},
{"learn":[3.102703811],"iteration":959,"passed_time":0.8197963166,"remaining_time":0.03415817986},
{"learn":[3.101469264],"iteration":960,"passed_time":0.8203757023,"remaining_time":0.03329308261},
{"learn":[3.09863569],"iteration":961,"passed_time":0.8209671958,"remaining_time":0.03242905763},
{"learn":[3.09645939],"iteration":962,"passed_time":0.8215350657,"remaining_time":0.031564691},
{"learn":[3.096240186],"iteration":963,"passed_time":0.8221123178,"remaining_time":0.03070128988},
{"learn":[3.094838828],"iteration":964,"passed_time":0.8227071537,"remaining_time":0.02983911956},
{"learn":[3.094176802],"iteration":965,"passed_time":0.8233673879,"remaining_time":0.02897980454},
{"learn":[3.093182279],"iteration":966,"passed_time":0.8239561175,"remaining_time":0.02811846109},
{"learn":[3.090150687],"iteration":967,"passed_time":0.8245489878,"remaining_time":0.02725781778},
{"learn":[3.088612829],"iteration":968,"passed_time":0.8251698338,"remaining_time":0.02639862213},
{"learn":[3.087153684],"iteration":969,"passed_time":0.8257312205,"remaining_time":0.02553807898},
{"learn":[3.085866843],"iteration":970,"passed_time":0.8263220208,"remaining_time":0.02467903049},
{"learn":[3.082669094],"iteration":971,"passed_time":0.8269404682,"remaining_time":0.02382133036},
{"learn":[3.081047548],"iteration":972,"passed_time":0.8275334801,"remaining_time":0.0229634162},
{"learn":[3.079684322],"iteration":973,"passed_time":0.8294976395,"remaining_time":0.02214264746},
{"learn":[3.07613431],"iteration":974,"passed_time":0.830443075,"remaining_time":0.02129341218},
{"learn":[3.074005935],"iteration":975,"passed_time":0.8311882185,"remaining_time":0.02043905455},
{"learn":[3.072988853],"iteration":976,"passed_time":0.8318052569,"remaining_time":0.01958190472},
{"learn":[3.072344268],"iteration":977,"passed_time":0.8323973828,"remaining_time":0.0187246855},
{"learn":[3.070654438],"iteration":978,"passed_time":0.8329745739,"remaining_time":0.01786768749},
{"learn":[3.069724506],"iteration":979,"passed_time":0.8335607355,"remaining_time":0.01701144358},
{"learn":[3.067763166],"iteration":980,"passed_time":0.8341364416,"remaining_time":0.0161555478},
{"learn":[3.066737893],"iteration":981,"passed_time":0.8347217701,"remaining_time":0.01530039904},
{"learn":[3.065248174],"iteration":982,"passed_time":0.8353739313,"remaining_time":0.01444695507},
{"learn":[3.063186837],"iteration":983,"passed_time":0.8359814673,"remaining_time":0.01359319459},
{"learn":[3.062880371],"iteration":984,"passed_time":0.8365730491,"remaining_time":0.0127396911},
{"learn":[3.061288645],"iteration":985,"passed_time":0.8372274549,"remaining_time":0.01188761092},
{"learn":[3.059970575],"iteration":986,"passed_time":0.837810832,"remaining_time":0.01103499576},
{"learn":[3.059576341],"iteration":987,"passed_time":0.8384074872,"remaining_time":0.01018308689},
{"learn":[3.058175919],"iteration":988,"passed_time":0.839398257,"remaining_time":0.009336077681},
{"learn":[3.056830702],"iteration":989,"passed_time":0.8400168617,"remaining_time":0.008485018805},
{"learn":[3.056336579],"iteration":990,"passed_time":0.8406018195,"remaining_time":0.007634123487},
{"learn":[3.055810414],"iteration":991,"passed_time":0.8411821308,"remaining_time":0.006783726861},
{"learn":[3.055476518],"iteration":992,"passed_time":0.8417501886,"remaining_time":0.005933787835},
{"learn":[3.053331734],"iteration":993,"passed_time":0.8423348718,"remaining_time":0.005084516329},
{"learn":[3.050890374],"iteration":994,"passed_time":0.8429185073,"remaining_time":0.004235771394},
{"learn":[3.04972623],"iteration":995,"passed_time":0.8438630683,"remaining_time":0.003389008307},
{"learn":[3.047217327],"iteration":996,"passed_time":0.8446041284,"remaining_time":0.002541436695},
{"learn":[3.047155483],"iteration":997,"passed_time":0.8454667849,"remaining_time":0.001694322214},
{"learn":[3.04430671],"iteration":998,"passed_time":0.8461388986,"remaining_time":0.0008469858845},
{"learn":[3.042664195],"iteration":999,"passed_time":0.8468193529,"remaining_time":0}
]}